Workbook

Sheet Instruções
B2: FACSS — CRM Otimizado (Clientes + Pipeline)
B3: Reconstrução da sua aba Clientes: 1 linha por cliente, atributos em colunas com listas suspensas, log de meses normalizado.
B5: Abas
B6: Clientes | C6: Um cliente por linha. Colunas de Status, Faturamento, Acesso, Fidelidade, Módulos, Treinamento e Evolução têm listas suspensas (padroniza o preenchimento). A coluna 'Health' é automática.
B7: Interações | C7: Substitui as 12 colunas de meses. Cada contato = 1 linha (Data, Cliente, Responsável, Tipo, Observação, Próximo passo). Migrei jun/jul como exemplo. Continue registrando aqui.
B8: Pipeline | C8: Funil de NOVOS clientes (os 29 lookalikes de RLR/Aperam/Sempre Volta). Estágio com dropdown; 'Valor ponderado' calcula sozinho (veículos × ticket × probabilidade do estágio).
B9: Dashboard | C9: Tudo automático por fórmula: carteira por status, faturamento, health, veículos, carga por responsável e funil comercial.
B10: Config | C10: Listas das suspensas e o Ticket (R$/veículo/mês) em P2 — edite com seu valor real.
B11: Como importar no Google Sheets | C11: Abra sua planilha → Arquivo → Importar → Enviar (faça upload deste .xlsx) → escolha 'Inserir nova(s) aba(s)'. As 6 abas entram sem apagar o que você já tem.
B12: Preencher | C12: As colunas em amarelo (Config P2) e as datas/próximas ações são pra você manter. Use as suspensas — não digite texto livre nos campos de status.
B13: Exemplo de linha (Clientes) | C13: ÁGUA BONITA | Ativo | Faturando | Diego | ... | 6 veículos | Não faz | Telemetria II | Sem fidelidade | Módulos operando | Desatualizado | Sem evolução → Health = 🟡 Atenção (fatura, mas treinamento desatualizado).

Sheet Dicionário de Aprendizado
A1: 📘 Dicionário de Aprendizado — CRM FACSS
A2: Termo | B2: Significado / O que representa | C2: Observações
A3: ABAS DA PLANILHA
A4: Instruções | B4: Aba-guia com o passo a passo e a lógica de montagem do CRM. | C4: Leia antes de preencher.
A5: Dashboard | B5: Painel de indicadores calculado automaticamente por fórmulas. | C5: Não edite manualmente.
A6: Clientes | B6: Cadastro da carteira: 1 linha por cliente. | C6: A coluna Health é automática.
A7: Interações | B7: Registro (log) de contatos: 1 linha por contato. | C7: Substituiu as antigas colunas de meses.
A8: Pipeline | B8: Funil de NOVOS clientes (prospecção comercial). | C8: Valor ponderado é automático.
A9: Config | B9: Listas suspensas e parâmetros da planilha. | C9: Não apagar; edite só os valores.
A10: STATUS DO CLIENTE
A11: Ativo | B11: Cliente já operando com o produto. | C11: Status da carteira.
A12: Período de teste | B12: Cliente em avaliação ou trial. | C12: Status da carteira.
A13: Proposta comercial | B13: Proposta enviada; cliente em decisão. | C13: Status da carteira.
A14: Prospecção | B14: Ainda em abordagem inicial. | C14: Status da carteira.
A15: FATURAMENTO
A16: Faturando | B16: Cliente gerando receita ativa.
A17: Sem faturar | B17: Cliente sem cobrança no momento.
A18: Faturamento inativo | B18: Já faturou, mas está parado.
A19: NÍVEL DE ACESSO (TELEMETRIA)
A20: Telemetria II | B20: Acesso e integração mais completos aos dados de telemetria.
A21: Telemetria I | B21: Acesso básico à telemetria.
A22: Sem acesso | B22: Sem integração de telemetria.
A23: SAÚDE DA CARTEIRA (HEALTH automático)
A24: Saudável | B24: Cliente em boa situação (verde). | C24: Calculado pelo sistema.
A25: Atenção | B25: Exige acompanhamento (amarelo). | C25: Calculado pelo sistema.
A26: Risco | B26: Risco de perda ou churn (vermelho). | C26: Calculado pelo sistema.
A27: Prospecção | B27: Ainda não é cliente efetivo.
A28: Sem dados (preencher) | B28: Faltam informações para calcular a saúde.
A29: FIDELIDADE, TREINAMENTO E EVOLUÇÃO
A30: Fidelidade 12 meses | B30: Contrato com fidelidade de 12 meses.
A31: Sem fidelidade | B31: Sem cláusula de fidelidade.
A32: Fidelizar | B32: Meta de conquistar a fidelidade do cliente.
A33: Módulos operando | B33: Módulos do produto em uso.
A34: Checar módulos | B34: Verificar quais módulos estão ativos.
A35: Atualizado | B35: Treinamento do cliente em dia.
A36: Desatualizado | B36: Treinamento pendente ou vencido.
A37: Com evolução | B37: Cliente evoluindo no uso do produto.
A38: Sem evolução | B38: Cliente estagnado no uso.
A39: SISTEMAS DE TELEMETRIA (fornecedores)
A40: AIKO | B40: Plataforma de rastreamento e telemetria.
A41: Trucks Control | B41: Plataforma de rastreamento e telemetria.
A42: Sascar | B42: Plataforma de rastreamento e telemetria.
A43: Link | B43: Acesso via link ou integração.
A44: Não faz | B44: Cliente não usa telemetria.
A45: ESTÁGIOS DO FUNIL (PIPELINE)
A46: Lead | B46: Oportunidade inicial identificada. | C46: Probabilidade 5%.
A47: Contato feito | B47: Primeiro contato realizado. | C47: Probabilidade 10%.
A48: Diagnóstico agendado | B48: Reunião de diagnóstico marcada. | C48: Probabilidade 25%.
A49: Diagnóstico feito | B49: Diagnóstico concluído. | C49: Probabilidade 40%.
A50: Proposta enviada | B50: Proposta comercial enviada. | C50: Probabilidade 60%.
A51: Negociação | B51: Em negociação final. | C51: Probabilidade 80%.
A52: Fechado - Ganho | B52: Negócio fechado com sucesso. | C52: Probabilidade 100%.
A53: Fechado - Perdido | B53: Oportunidade perdida. | C53: Probabilidade 0%.
A54: CANAIS DE AQUISIÇÃO
A55: Outbound LinkedIn | B55: Prospecção ativa via LinkedIn.
A56: Outbound e-mail | B56: Prospecção ativa via e-mail.
A57: Telefone | B57: Contato direto por telefone.
A58: WhatsApp | B58: Contato direto por WhatsApp.
A59: Indicação | B59: Cliente veio por indicação.
A60: Evento | B60: Contato originado em evento.
A61: Parceria | B61: Origem via parceiro.
A62: TIPOS DE INTERAÇÃO
A63: Interação | B63: Contato genérico registrado.
A64: Reunião | B64: Encontro ou call.
A65: Treinamento | B65: Sessão de capacitação.
A66: Condução assistida | B66: Acompanhamento operacional guiado.
A67: Cobrança | B67: Contato sobre pagamento.
A68: Suporte | B68: Atendimento de suporte.
A69: PRIORIDADE (PIPELINE)
A70: A | B70: Alta prioridade.
A71: B | B71: Média prioridade.
A72: C | B72: Baixa prioridade.
A73: MÉTRICAS E CONCEITOS
A74: Valor ponderado | B74: Receita esperada do funil: veículos x ticket x probabilidade do estágio. | C74: Coluna do Pipeline.
A75: Ticket (R$ por veículo ao mês) | B75: Preço médio por veículo por mês (premissa base). | C75: Definido na aba Config.
A76: Prospects (total) | B76: Total de oportunidades no funil. | C76: Indicador do Dashboard.
A77: Health (auto) | B77: Classificação automática de saúde do cliente. | C77: Coluna da aba Clientes.

Sheet Dashboard
B2: FACSS — Painel de Clientes & Pipeline
B3: Atualiza automaticamente conforme você edita as abas Clientes e Pipeline
B5: Carteira por status | E5: Health da carteira | H5: Pipeline comercial (novos)
B7: Ativos | C7: =COUNTIF(Clientes!$B$2:$B$51,"Ativo") -> 16 | E7: 🟢 Saudável | F7: =COUNTIF(Clientes!$E$2:$E$47,E7) -> 6 | H7: Lead | I7: =COUNTIF(Pipeline!$H$2:$H$300,"Lead") -> 24
B8: Período de teste | C8: =COUNTIF(Clientes!$B$2:$B$51,"Período de teste") -> 5 | E8: 🟡 Atenção | F8: =COUNTIF(Clientes!$E$2:$E$47,E8) -> 17 | H8: Contato feito | I8: =COUNTIF(Pipeline!$H$2:$H$300,"Contato feito") -> 0
B9: Proposta comercial | C9: =COUNTIF(Clientes!$B$2:$B$51,"Proposta comercial") -> 3 | E9: 🔴 Risco | F9: =COUNTIF(Clientes!$E$2:$E$47,E9) -> 1 | H9: Diagnóstico agendado | I9: =COUNTIF(Pipeline!$H$2:$H$300,"Diagnóstico agendado") -> 0
B10: Prospecção | C10: =COUNTIF(Clientes!$B$2:$B$51,"Prospecção") -> 6 | E10: ⚪ Sem dados | F10: =COUNTIF(Clientes!$E$2:$E$47,E10) -> 22 | H10: Diagnóstico feito | I10: =COUNTIF(Pipeline!$H$2:$H$300,"Diagnóstico feito") -> 0
B11: Clientes Inativo | C11: =COUNTIF(Clientes!$B$2:$B$48,"Inativo") -> 3 | H11: Proposta enviada | I11: =COUNTIF(Pipeline!$H$2:$H$300,"Proposta enviada") -> 0
B12: POCs Sem Evolução | C12: =COUNTIF(Clientes!$B$2:$B$51,"POC Sem Evolução") -> 10 | H12: Negociação | I12: =COUNTIF(Pipeline!$H$2:$H$300,"Negociação") -> 0
B13: Prospecção sem Sucesso | C13: =COUNTIF(Clientes!$B$2:$B$51,"Prospecção sem Sucesso") -> 3 | H13: Fechado - Ganho | I13: =COUNTIF(Pipeline!$H$2:$H$300,"Fechado - Ganho") -> 0
B15: Faturamento | E15: Operação
B17: Faturando | C17: =COUNTIF(Clientes!$C$2:$C$48,"Faturando") -> 15 | E17: Total de veículos | F17: =SUM(Clientes!$K$2:$K$501) -> 2072 | H17: Valor ponderado (R$/mês) | I17: =SUM(Pipeline!$K$2:$K$300) -> 0
B18: Sem faturar | C18: =COUNTIF(Clientes!$C$2:$C$48,"Sem faturar") -> 0 | E18: Interações registradas | F18: =COUNTA('Interações'!$A$2:$A$204) -> 127 | H18: Prospects (total) | I18: =COUNTA(Pipeline!$B$2:$B$300) -> 24
E19: Clientes p/ Diego | F19: =COUNTIF(Clientes!$D$2:$D$51,"Diego") -> 22
E20: Clientes p/ Guilherme | F20: =COUNTIF(Clientes!$D$2:$D$51,"Guilherme") -> 22
E21: Clientes p/ Pablo | F21: =COUNTIF(Clientes!$D$2:$D$51,"Pablo") -> 1

Sheet Clientes
A1: Cliente | B1: Status | C1: Faturamento | D1: Resp. | E1: Health | F1: CNPJ | G1: Contato | H1: Telefone | I1: E-mail | J1: Início | L1: Módulos | M1: Sistema Jornada | N1: Nível de acesso | O1: Fidelidade | P1: Treinamento | Q1: Evolução | R1: Última interação
A2: AAS SOLUÇÕES | B2: POC Sem Evolução | C2: Faturamento inativo | D2: Diego | E2: =IF(OR($B2="POC Sem Evolução",$B2="Prospecção Sem Sucesso",$B2="Inativo",$B2="Prospecção"), "⚪ Sem dados",IF($C2="Faturando",IF($Q2="Com evolução","🟢 Saudável",IF($Q2="Sem evolução", "🟡 Atenção",IF(AND($P2="Capacitação Efetiva",$L2="Módulos operando"),"🟢 Saudável","🟡 Atenção"))), IF(AND($B2="Ativo",$C2="Faturamento inativo"),"🔴 Risco",IF($C2="","⚪ Sem dados","🟡 Atenção")))) -> ⚪ Sem dados | F2: 07.453115/0001-80 | G2: Luiz Fernando | H2: (31) 97202-5800 | I2: administrtivo@solucoesaas.com.br | J2: 46009 | K2: =COUNTIFS('Módulos'!$G$2:$G$2464,A2,'Módulos'!$I$2:$I$2464,"ATIVO") -> 1 | L2: Telemetria suspensa | M2: Sem dados | N2: Sem acesso | O2: Sem fidelidade | P2: Inativado | Q2: Inativado | R2: 46149
A3: ÁGUA BONITA | B3: Ativo | C3: Faturando | D3: Diego | E3: =IF(OR($B3="POC Sem Evolução",$B3="Prospecção Sem Sucesso",$B3="Inativo",$B3="Prospecção"), "⚪ Sem dados",IF($C3="Faturando",IF($Q3="Com evolução","🟢 Saudável",IF($Q3="Sem evolução", "🟡 Atenção",IF(AND($P3="Capacitação Efetiva",$L3="Módulos operando"),"🟢 Saudável","🟡 Atenção"))), IF(AND($B3="Ativo",$C3="Faturamento inativo"),"🔴 Risco",IF($C3="","⚪ Sem dados","🟡 Atenção")))) -> 🟡 Atenção | F3: 01.042.849/0001-90 | G3: Diego | H3: (31) 3147-0266 / 99619-5320 | I3: diegoapc@yahoo.com.br | J3: 45939 | K3: =COUNTIFS('Módulos'!$G$2:$G$2464,A3,'Módulos'!$I$2:$I$2464,"ATIVO") -> 6 | L3: Módulos operando | M3: Não faz | N3: Telemetria II | O3: Sem fidelidade | P3: Realizar Capacitação | Q3: Sem evolução | R3: 46209
A4: APERAM Carvão | B4: Ativo | C4: Faturando | D4: Guilherme | E4: =IF(OR($B4="POC Sem Evolução",$B4="Prospecção Sem Sucesso",$B4="Inativo",$B4="Prospecção"), "⚪ Sem dados",IF($C4="Faturando",IF($Q4="Com evolução","🟢 Saudável",IF($Q4="Sem evolução", "🟡 Atenção",IF(AND($P4="Capacitação Efetiva",$L4="Módulos operando"),"🟢 Saudável","🟡 Atenção"))), IF(AND($B4="Ativo",$C4="Faturamento inativo"),"🔴 Risco",IF($C4="","⚪ Sem dados","🟡 Atenção")))) -> 🟡 Atenção | F4: 18.238.980/0094-20 | G4: Ailton | H4: (33) 99849-3803 | I4: ailton.azevedo@aperam.com.br | J4: 45887 | K4: =COUNTIFS('Módulos'!$G$2:$G$2464,A4,'Módulos'!$I$2:$I$2464,"ATIVO") -> 118 | L4: Módulos operando | M4: AIKO | N4: Telemetria I | O4: Sem fidelidade | P4: Capacitação Efetiva | Q4: Sem evolução | R4: 46216
A5: APERAM Madeira | B5: Período de teste | C5: Faturamento inativo | D5: Pablo | E5: =IF(OR($B5="POC Sem Evolução",$B5="Prospecção Sem Sucesso",$B5="Inativo",$B5="Prospecção"), "⚪ Sem dados",IF($C5="Faturando",IF($Q5="Com evolução","🟢 Saudável",IF($Q5="Sem evolução", "🟡 Atenção",IF(AND($P5="Capacitação Efetiva",$L5="Módulos operando"),"🟢 Saudável","🟡 Atenção"))), IF(AND($B5="Ativo",$C5="Faturamento inativo"),"🔴 Risco",IF($C5="","⚪ Sem dados","🟡 Atenção")))) -> 🟡 Atenção | F5: - | G5: João / Adilson Alves (Supervisor) | H5: (33) 99915-4208 / (38) 9906-3301 | I5: adilsom.alvesfernandes@aperam.com | J5: 45887 | K5: =COUNTIFS('Módulos'!$G$2:$G$2464,A5,'Módulos'!$I$2:$I$2464,"ATIVO") -> 4 | L5: Módulos operando | M5: Sem dados | N5: Sem acesso | O5: Fidelizar | P5: Realizar Capacitação | Q5: Em POC | R5: 46216
A6: BEIRA RIO | B6: Ativo | C6: Faturando | D6: Diego | E6: =IF(OR($B6="POC Sem Evolução",$B6="Prospecção Sem Sucesso",$B6="Inativo",$B6="Prospecção"), "⚪ Sem dados",IF($C6="Faturando",IF($Q6="Com evolução","🟢 Saudável",IF($Q6="Sem evolução", "🟡 Atenção",IF(AND($P6="Capacitação Efetiva",$L6="Módulos operando"),"🟢 Saudável","🟡 Atenção"))), IF(AND($B6="Ativo",$C6="Faturamento inativo"),"🔴 Risco",IF($C6="","⚪ Sem dados","🟡 Atenção")))) -> 🟡 Atenção | F6: 16.883.860/0001-50 | G6: Breno / Arthur | H6: (38) 98402-3720 | I6: breno@grupobeirario.com.br / arthur@grupobeirario.com.br | J6: 46017 | K6: =COUNTIFS('Módulos'!$G$2:$G$2464,A6,'Módulos'!$I$2:$I$2464,"ATIVO") -> 29 | L6: Módulos operando | M6: Sascar | N6: Telemetria II | O6: Sem fidelidade | P6: Capacitação Efetiva | Q6: Sem evolução | R6: 46225
A7: BRITO SERVIÇO | B7: POC Sem Evolução | C7: Faturamento inativo | D7: Guilherme | E7: =IF(OR($B7="POC Sem Evolução",$B7="Prospecção Sem Sucesso",$B7="Inativo",$B7="Prospecção"), "⚪ Sem dados",IF($C7="Faturando",IF($Q7="Com evolução","🟢 Saudável",IF($Q7="Sem evolução", "🟡 Atenção",IF(AND($P7="Capacitação Efetiva",$L7="Módulos operando"),"🟢 Saudável","🟡 Atenção"))), IF(AND($B7="Ativo",$C7="Faturamento inativo"),"🔴 Risco",IF($C7="","⚪ Sem dados","🟡 Atenção")))) -> ⚪ Sem dados | G7: Eric Julian | H7: (31) 99228-1313 | I7: ericjulian@britoservicos.com.br | J7: 45915 | K7: =COUNTIFS('Módulos'!$G$2:$G$2464,A7,'Módulos'!$I$2:$I$2464,"ATIVO") -> 0 | L7: Telemetria suspensa | M7: Sem dados | N7: Sem acesso | O7: Sem fidelidade | P7: Inativado | Q7: Inativado | R7: 46170
A8: CONFINS | B8: Proposta comercial | C8: Faturamento inativo | D8: Guilherme | E8: =IF(OR($B8="POC Sem Evolução",$B8="Prospecção Sem Sucesso",$B8="Inativo",$B8="Prospecção"), "⚪ Sem dados",IF($C8="Faturando",IF($Q8="Com evolução","🟢 Saudável",IF($Q8="Sem evolução", "🟡 Atenção",IF(AND($P8="Capacitação Efetiva",$L8="Módulos operando"),"🟢 Saudável","🟡 Atenção"))), IF(AND($B8="Ativo",$C8="Faturamento inativo"),"🔴 Risco",IF($C8="","⚪ Sem dados","🟡 Atenção")))) -> 🟡 Atenção | F8: - | G8: - | H8: - | I8: - | K8: =COUNTIFS('Módulos'!$G$2:$G$2464,A8,'Módulos'!$I$2:$I$2464,"ATIVO") -> 4 | L8: Módulos operando | M8: Sem dados | N8: Sem acesso | O8: Fidelizar | P8: Realizar Capacitação | Q8: Em POC | R8: 46219
A9: COOPERAUTO | B9: Prospecção | C9: Faturamento inativo | D9: Guilherme | E9: =IF(OR($B9="POC Sem Evolução",$B9="Prospecção Sem Sucesso",$B9="Inativo",$B9="Prospecção"), "⚪ Sem dados",IF($C9="Faturando",IF($Q9="Com evolução","🟢 Saudável",IF($Q9="Sem evolução", "🟡 Atenção",IF(AND($P9="Capacitação Efetiva",$L9="Módulos operando"),"🟢 Saudável","🟡 Atenção"))), IF(AND($B9="Ativo",$C9="Faturamento inativo"),"🔴 Risco",IF($C9="","⚪ Sem dados","🟡 Atenção")))) -> ⚪ Sem dados | F9: - | G9: - | H9: - | I9: - | K9: =COUNTIFS('Módulos'!$G$2:$G$2464,A9,'Módulos'!$I$2:$I$2464,"ATIVO") -> 0 | L9: Checar módulos | M9: Sem dados | N9: Sem acesso | O9: Fidelizar | P9: Realizar Capacitação | Q9: Sem dados
A10: COOPERVALE | B10: Prospecção sem Sucesso | C10: Faturamento inativo | D10: Diego | E10: =IF(OR($B10="POC Sem Evolução",$B10="Prospecção Sem Sucesso",$B10="Inativo",$B10="Prospecção"), "⚪ Sem dados",IF($C10="Faturando",IF($Q10="Com evolução","🟢 Saudável",IF($Q10="Sem evolução", "🟡 Atenção",IF(AND($P10="Capacitação Efetiva",$L10="Módulos operando"),"🟢 Saudável","🟡 Atenção"))), IF(AND($B10="Ativo",$C10="Faturamento inativo"),"🔴 Risco",IF($C10="","⚪ Sem dados","🟡 Atenção")))) -> ⚪ Sem dados | F10: - | G10: - | H10: - | I10: - | K10: =COUNTIFS('Módulos'!$G$2:$G$2464,A10,'Módulos'!$I$2:$I$2464,"ATIVO") -> 0 | L10: Telemetria suspensa | M10: Sem dados | N10: Sem acesso | O10: Fidelizar | P10: Inativado | Q10: Inativado | R10: 46212
A11: DELLMAR | B11: Prospecção | C11: Faturamento inativo | D11: Diego | E11: =IF(OR($B11="POC Sem Evolução",$B11="Prospecção Sem Sucesso",$B11="Inativo",$B11="Prospecção"), "⚪ Sem dados",IF($C11="Faturando",IF($Q11="Com evolução","🟢 Saudável",IF($Q11="Sem evolução", "🟡 Atenção",IF(AND($P11="Capacitação Efetiva",$L11="Módulos operando"),"🟢 Saudável","🟡 Atenção"))), IF(AND($B11="Ativo",$C11="Faturamento inativo"),"🔴 Risco",IF($C11="","⚪ Sem dados","🟡 Atenção")))) -> ⚪ Sem dados | F11: 13.254.104/0001-74 | G11: Rogerio | H11: (11) 99007-8588 | I11: rogerio.souza@dellmar.com.br | K11: =COUNTIFS('Módulos'!$G$2:$G$2464,A11,'Módulos'!$I$2:$I$2464,"ATIVO") -> 0 | L11: Checar módulos | M11: Sem dados | N11: Sem acesso | O11: Fidelizar | P11: Realizar Capacitação | Q11: Sem dados
A12: DNA | B12: Ativo | C12: Faturando | D12: Diego | E12: =IF(OR($B12="POC Sem Evolução",$B12="Prospecção Sem Sucesso",$B12="Inativo",$B12="Prospecção"), "⚪ Sem dados",IF($C12="Faturando",IF($Q12="Com evolução","🟢 Saudável",IF($Q12="Sem evolução", "🟡 Atenção",IF(AND($P12="Capacitação Efetiva",$L12="Módulos operando"),"🟢 Saudável","🟡 Atenção"))), IF(AND($B12="Ativo",$C12="Faturamento inativo"),"🔴 Risco",IF($C12="","⚪ Sem dados","🟡 Atenção")))) -> 🟡 Atenção | F12: 21.479.020/0001-67 | G12: Deivison | H12: (31) 99731-9189 | I12: dna.deivson@gmail.com / dna.mariana93@gmail.com | J12: 45901 | K12: =COUNTIFS('Módulos'!$G$2:$G$2464,A12,'Módulos'!$I$2:$I$2464,"ATIVO") -> 11 | L12: Módulos operando | M12: Não faz | N12: Telemetria II | O12: Fidelidade 12 meses | P12: Capacitação Efetiva | Q12: Sem evolução | R12: 46204
A13: EMF LOGÍSTICA | B13: POC Sem Evolução | C13: Faturamento inativo | D13: Guilherme | E13: =IF(OR($B13="POC Sem Evolução",$B13="Prospecção Sem Sucesso",$B13="Inativo",$B13="Prospecção"), "⚪ Sem dados",IF($C13="Faturando",IF($Q13="Com evolução","🟢 Saudável",IF($Q13="Sem evolução", "🟡 Atenção",IF(AND($P13="Capacitação Efetiva",$L13="Módulos operando"),"🟢 Saudável","🟡 Atenção"))), IF(AND($B13="Ativo",$C13="Faturamento inativo"),"🔴 Risco",IF($C13="","⚪ Sem dados","🟡 Atenção")))) -> ⚪ Sem dados | F13: 05.151.226/0001-07 | G13: Rafael | H13: (31) 9377-1430 | I13: rafael.oliveira@emflogistica.com.br / pedro.estrugiaki@emflogistica.com.br | J13: 45936 | K13: =COUNTIFS('Módulos'!$G$2:$G$2464,A13,'Módulos'!$I$2:$I$2464,"ATIVO") -> 44 | L13: Módulos operando | M13: Trucks Control | N13: Telemetria II | O13: Fidelizar | P13: Inativado | Q13: Inativado | R13: 46219
A14: EXPRESSO TRANSPORTE | B14: Ativo | C14: Faturando | D14: Diego | E14: =IF(OR($B14="POC Sem Evolução",$B14="Prospecção Sem Sucesso",$B14="Inativo",$B14="Prospecção"), "⚪ Sem dados",IF($C14="Faturando",IF($Q14="Com evolução","🟢 Saudável",IF($Q14="Sem evolução", "🟡 Atenção",IF(AND($P14="Capacitação Efetiva",$L14="Módulos operando"),"🟢 Saudável","🟡 Atenção"))), IF(AND($B14="Ativo",$C14="Faturamento inativo"),"🔴 Risco",IF($C14="","⚪ Sem dados","🟡 Atenção")))) -> 🟡 Atenção | F14: 27.892.478/0001-20 | G14: Marcos Gabriel | H14: (31) 97135-8694 | I14: administrativo@expressotransporte.com | J14: 46024 | K14: =COUNTIFS('Módulos'!$G$2:$G$2464,A14,'Módulos'!$I$2:$I$2464,"ATIVO") -> 19 | L14: Módulos operando | M14: Link | N14: Telemetria II | O14: Sem fidelidade | P14: Capacitação em Desenvolvimento | Q14: Sem evolução | R14: 46227
A15: FASI | B15: Período de teste | C15: Faturamento inativo | D15: Diego | E15: =IF(OR($B15="POC Sem Evolução",$B15="Prospecção Sem Sucesso",$B15="Inativo",$B15="Prospecção"), "⚪ Sem dados",IF($C15="Faturando",IF($Q15="Com evolução","🟢 Saudável",IF($Q15="Sem evolução", "🟡 Atenção",IF(AND($P15="Capacitação Efetiva",$L15="Módulos operando"),"🟢 Saudável","🟡 Atenção"))), IF(AND($B15="Ativo",$C15="Faturamento inativo"),"🔴 Risco",IF($C15="","⚪ Sem dados","🟡 Atenção")))) -> 🟡 Atenção | F15: 03.886.930/0001-82 | G15: Fabiano / João | H15: (31) 99957-6831 / (31) 99305-0034 | I15: fabianoalex@fasitransportes.com.br | J15: 45979 | K15: =COUNTIFS('Módulos'!$G$2:$G$2464,A15,'Módulos'!$I$2:$I$2464,"ATIVO") -> 4 | L15: Módulos operando | M15: Sem dados | N15: Telemetria II | O15: Fidelizar | P15: Capacitação em Desenvolvimento | Q15: Em POC | R15: 46217
A16: GERDAU LENARGE | B16: Inativo | C16: Faturamento inativo | D16: Guilherme | E16: =IF(OR($B16="POC Sem Evolução",$B16="Prospecção Sem Sucesso",$B16="Inativo",$B16="Prospecção"), "⚪ Sem dados",IF($C16="Faturando",IF($Q16="Com evolução","🟢 Saudável",IF($Q16="Sem evolução", "🟡 Atenção",IF(AND($P16="Capacitação Efetiva",$L16="Módulos operando"),"🟢 Saudável","🟡 Atenção"))), IF(AND($B16="Ativo",$C16="Faturamento inativo"),"🔴 Risco",IF($C16="","⚪ Sem dados","🟡 Atenção")))) -> ⚪ Sem dados | F16: - | G16: - | H16: - | I16: - | K16: =COUNTIFS('Módulos'!$G$2:$G$2464,A16,'Módulos'!$I$2:$I$2464,"ATIVO") -> 33 | L16: Telemetria suspensa | M16: Sem dados | N16: Sem acesso | O16: Sem fidelidade | P16: Inativado | Q16: Inativado
A17: GFM | B17: Ativo | C17: Faturando | D17: Diego | E17: =IF(OR($B17="POC Sem Evolução",$B17="Prospecção Sem Sucesso",$B17="Inativo",$B17="Prospecção"), "⚪ Sem dados",IF($C17="Faturando",IF($Q17="Com evolução","🟢 Saudável",IF($Q17="Sem evolução", "🟡 Atenção",IF(AND($P17="Capacitação Efetiva",$L17="Módulos operando"),"🟢 Saudável","🟡 Atenção"))), IF(AND($B17="Ativo",$C17="Faturamento inativo"),"🔴 Risco",IF($C17="","⚪ Sem dados","🟡 Atenção")))) -> 🟢 Saudável | F17: - | G17: - | H17: - | I17: - | K17: =COUNTIFS('Módulos'!$G$2:$G$2464,A17,'Módulos'!$I$2:$I$2464,"ATIVO") -> 9 | L17: Módulos operando | M17: Sem dados | N17: Telemetria II | O17: Fidelidade 12 meses | P17: Capacitação Efetiva | Q17: Com evolução | R17: 46217
A18: GTS | B18: POC Sem Evolução | C18: Faturamento inativo | D18: Diego | E18: =IF(OR($B18="POC Sem Evolução",$B18="Prospecção Sem Sucesso",$B18="Inativo",$B18="Prospecção"), "⚪ Sem dados",IF($C18="Faturando",IF($Q18="Com evolução","🟢 Saudável",IF($Q18="Sem evolução", "🟡 Atenção",IF(AND($P18="Capacitação Efetiva",$L18="Módulos operando"),"🟢 Saudável","🟡 Atenção"))), IF(AND($B18="Ativo",$C18="Faturamento inativo"),"🔴 Risco",IF($C18="","⚪ Sem dados","🟡 Atenção")))) -> ⚪ Sem dados | F18: - | G18: Jânio | H18: (11) 94187-733 | I18: janio.alves@gtstransportes.com.br | J18: 45973 | K18: =COUNTIFS('Módulos'!$G$2:$G$2464,A18,'Módulos'!$I$2:$I$2464,"ATIVO") -> 0 | L18: Telemetria suspensa | M18: Sem dados | N18: Sem acesso | O18: Sem fidelidade | P18: Inativado | Q18: Inativado | R18: 46189
A19: HERTEX | B19: Período de teste | C19: Faturamento inativo | D19: Diego | E19: =IF(OR($B19="POC Sem Evolução",$B19="Prospecção Sem Sucesso",$B19="Inativo",$B19="Prospecção"), "⚪ Sem dados",IF($C19="Faturando",IF($Q19="Com evolução","🟢 Saudável",IF($Q19="Sem evolução", "🟡 Atenção",IF(AND($P19="Capacitação Efetiva",$L19="Módulos operando"),"🟢 Saudável","🟡 Atenção"))), IF(AND($B19="Ativo",$C19="Faturamento inativo"),"🔴 Risco",IF($C19="","⚪ Sem dados","🟡 Atenção")))) -> 🟡 Atenção | F19: 24.070.142/0001-93 | G19: Lau | H19: (31) 98437-3092 | I19: - | J19: 45798 | K19: =COUNTIFS('Módulos'!$G$2:$G$2464,A19,'Módulos'!$I$2:$I$2464,"ATIVO") -> 3 | L19: Módulos operando | M19: Fastmine | N19: Telemetria II | O19: Fidelizar | P19: Capacitação em Desenvolvimento | Q19: Em POC | R19: 46219
A20: JAF | B20: Ativo | C20: Faturando | D20: Diego | E20: =IF(OR($B20="POC Sem Evolução",$B20="Prospecção Sem Sucesso",$B20="Inativo",$B20="Prospecção"), "⚪ Sem dados",IF($C20="Faturando",IF($Q20="Com evolução","🟢 Saudável",IF($Q20="Sem evolução", "🟡 Atenção",IF(AND($P20="Capacitação Efetiva",$L20="Módulos operando"),"🟢 Saudável","🟡 Atenção"))), IF(AND($B20="Ativo",$C20="Faturamento inativo"),"🔴 Risco",IF($C20="","⚪ Sem dados","🟡 Atenção")))) -> 🟡 Atenção | F20: 09.185.563/0001-76 | G20: Maria Clara | H20: (31) 99959-3176 | I20: controle.diesel@jaftransporte.com.br | J20: 46087 | K20: =COUNTIFS('Módulos'!$G$2:$G$2464,A20,'Módulos'!$I$2:$I$2464,"ATIVO") -> 56 | L20: Módulos operando | M20: SAT | N20: Telemetria II | O20: Fidelidade 12 meses | P20: Capacitação em Desenvolvimento | Q20: Sem evolução | R20: 46225
A21: LENARGE | B21: Ativo | C21: Faturando | D21: Guilherme | E21: =IF(OR($B21="POC Sem Evolução",$B21="Prospecção Sem Sucesso",$B21="Inativo",$B21="Prospecção"), "⚪ Sem dados",IF($C21="Faturando",IF($Q21="Com evolução","🟢 Saudável",IF($Q21="Sem evolução", "🟡 Atenção",IF(AND($P21="Capacitação Efetiva",$L21="Módulos operando"),"🟢 Saudável","🟡 Atenção"))), IF(AND($B21="Ativo",$C21="Faturamento inativo"),"🔴 Risco",IF($C21="","⚪ Sem dados","🟡 Atenção")))) -> 🟢 Saudável | F21: 02.870.124/0001-53 | G21: Matheus | H21: (31) 99969-5289 | I21: matheus@lenarge.com.br | J21: 45566 | K21: =COUNTIFS('Módulos'!$G$2:$G$2464,A21,'Módulos'!$I$2:$I$2464,"ATIVO") -> 1346 | L21: Módulos operando | M21: Sascar | N21: Telemetria I | O21: Sem fidelidade | P21: Capacitação Efetiva | Q21: Com evolução
A22: M1 | B22: Ativo | C22: Faturando | D22: Diego | E22: =IF(OR($B22="POC Sem Evolução",$B22="Prospecção Sem Sucesso",$B22="Inativo",$B22="Prospecção"), "⚪ Sem dados",IF($C22="Faturando",IF($Q22="Com evolução","🟢 Saudável",IF($Q22="Sem evolução", "🟡 Atenção",IF(AND($P22="Capacitação Efetiva",$L22="Módulos operando"),"🟢 Saudável","🟡 Atenção"))), IF(AND($B22="Ativo",$C22="Faturamento inativo"),"🔴 Risco",IF($C22="","⚪ Sem dados","🟡 Atenção")))) -> 🟡 Atenção | F22: 41.568.245/0001-05 | G22: Matheus | H22: (31) 99969-5289 | I22: matheus@lenarge.com.br | J22: 45901 | K22: =COUNTIFS('Módulos'!$G$2:$G$2464,A22,'Módulos'!$I$2:$I$2464,"ATIVO") -> 6 | L22: Módulos operando | M22: Sem dados | N22: Telemetria II | O22: Fidelidade 12 meses | P22: Capacitação Efetiva | Q22: Sem evolução
A23: MAGNO | B23: Ativo | C23: Faturando | D23: Diego | E23: =IF(OR($B23="POC Sem Evolução",$B23="Prospecção Sem Sucesso",$B23="Inativo",$B23="Prospecção"), "⚪ Sem dados",IF($C23="Faturando",IF($Q23="Com evolução","🟢 Saudável",IF($Q23="Sem evolução", "🟡 Atenção",IF(AND($P23="Capacitação Efetiva",$L23="Módulos operando"),"🟢 Saudável","🟡 Atenção"))), IF(AND($B23="Ativo",$C23="Faturamento inativo"),"🔴 Risco",IF($C23="","⚪ Sem dados","🟡 Atenção")))) -> 🟢 Saudável | F23: 34.391.213/0001-03 | G23: Reinaldo | H23: (31) 98793-0832 | I23: magnotransportes777@gmail.com | J23: 45901 | K23: =COUNTIFS('Módulos'!$G$2:$G$2464,A23,'Módulos'!$I$2:$I$2464,"ATIVO") -> 7 | L23: Módulos operando | M23: Sem dados | N23: Telemetria II | O23: Sem fidelidade | P23: Capacitação Efetiva | Q23: Com evolução
A24: MALIBU | B24: Prospecção | C24: Faturamento inativo | D24: Diego | E24: =IF(OR($B24="POC Sem Evolução",$B24="Prospecção Sem Sucesso",$B24="Inativo",$B24="Prospecção"), "⚪ Sem dados",IF($C24="Faturando",IF($Q24="Com evolução","🟢 Saudável",IF($Q24="Sem evolução", "🟡 Atenção",IF(AND($P24="Capacitação Efetiva",$L24="Módulos operando"),"🟢 Saudável","🟡 Atenção"))), IF(AND($B24="Ativo",$C24="Faturamento inativo"),"🔴 Risco",IF($C24="","⚪ Sem dados","🟡 Atenção")))) -> ⚪ Sem dados | F24: 97.442.123/0001-14 | G24: Fernando | H24: - | I24: fernando.miranda@malibutransportes.com.br | K24: =COUNTIFS('Módulos'!$G$2:$G$2464,A24,'Módulos'!$I$2:$I$2464,"ATIVO") -> 0 | L24: Checar módulos | M24: Sem dados | N24: Sem acesso | O24: Fidelizar | P24: Realizar Capacitação | Q24: Sem dados
A25: M&J | B25: Ativo | C25: Faturando | D25: Diego | E25: =IF(OR($B25="POC Sem Evolução",$B25="Prospecção Sem Sucesso",$B25="Inativo",$B25="Prospecção"), "⚪ Sem dados",IF($C25="Faturando",IF($Q25="Com evolução","🟢 Saudável",IF($Q25="Sem evolução", "🟡 Atenção",IF(AND($P25="Capacitação Efetiva",$L25="Módulos operando"),"🟢 Saudável","🟡 Atenção"))), IF(AND($B25="Ativo",$C25="Faturamento inativo"),"🔴 Risco",IF($C25="","⚪ Sem dados","🟡 Atenção")))) -> 🟡 Atenção | F25: 55.725.850/0001-49 | G25: Nayara | H25: (31) 97500-6409 | I25: nayara.moraes@lenarge.com.br | J25: 45952 | K25: =COUNTIFS('Módulos'!$G$2:$G$2464,A25,'Módulos'!$I$2:$I$2464,"ATIVO") -> 0 | L25: Módulos operando | M25: Sem dados | N25: Sem acesso | O25: Fidelidade 12 meses | P25: Capacitação Efetiva | Q25: Sem evolução
A26: MRX | B26: POC Sem Evolução | C26: Faturamento inativo | D26: Guilherme | E26: =IF(OR($B26="POC Sem Evolução",$B26="Prospecção Sem Sucesso",$B26="Inativo",$B26="Prospecção"), "⚪ Sem dados",IF($C26="Faturando",IF($Q26="Com evolução","🟢 Saudável",IF($Q26="Sem evolução", "🟡 Atenção",IF(AND($P26="Capacitação Efetiva",$L26="Módulos operando"),"🟢 Saudável","🟡 Atenção"))), IF(AND($B26="Ativo",$C26="Faturamento inativo"),"🔴 Risco",IF($C26="","⚪ Sem dados","🟡 Atenção")))) -> ⚪ Sem dados | F26: 26.586.645/001-41 | G26: Paulo Sérgio | H26: (31) 99670-0159 | I26: paulo.sergio@mrxtransportes.com | J26: 46037 | K26: =COUNTIFS('Módulos'!$G$2:$G$2464,A26,'Módulos'!$I$2:$I$2464,"ATIVO") -> 1 | L26: Telemetria suspensa | M26: Sem dados | N26: Sem acesso | O26: Sem fidelidade | P26: Inativado | Q26: Inativado | R26: 46158
A27: NOVA MINERAIS | B27: Ativo | C27: Faturamento inativo | D27: Guilherme | E27: =IF(OR($B27="POC Sem Evolução",$B27="Prospecção Sem Sucesso",$B27="Inativo",$B27="Prospecção"), "⚪ Sem dados",IF($C27="Faturando",IF($Q27="Com evolução","🟢 Saudável",IF($Q27="Sem evolução", "🟡 Atenção",IF(AND($P27="Capacitação Efetiva",$L27="Módulos operando"),"🟢 Saudável","🟡 Atenção"))), IF(AND($B27="Ativo",$C27="Faturamento inativo"),"🔴 Risco",IF($C27="","⚪ Sem dados","🟡 Atenção")))) -> 🔴 Risco | K27: =COUNTIFS('Módulos'!$G$2:$G$2464,A27,'Módulos'!$I$2:$I$2464,"ATIVO") -> 0 | L27: Módulos operando | M27: Sem dados | N27: Sem acesso | O27: Fidelizar | P27: Capacitação Efetiva | Q27: Sem dados
A28: P&W | B28: Proposta comercial | C28: Faturamento inativo | D28: Guilherme | E28: =IF(OR($B28="POC Sem Evolução",$B28="Prospecção Sem Sucesso",$B28="Inativo",$B28="Prospecção"), "⚪ Sem dados",IF($C28="Faturando",IF($Q28="Com evolução","🟢 Saudável",IF($Q28="Sem evolução", "🟡 Atenção",IF(AND($P28="Capacitação Efetiva",$L28="Módulos operando"),"🟢 Saudável","🟡 Atenção"))), IF(AND($B28="Ativo",$C28="Faturamento inativo"),"🔴 Risco",IF($C28="","⚪ Sem dados","🟡 Atenção")))) -> 🟡 Atenção | F28: 08.183.084/0001-58 | G28: Kener | H28: (31) 99484-0038 | I28: kener.silva@pwtransporte.com.br | J28: 45997 | K28: =COUNTIFS('Módulos'!$G$2:$G$2464,A28,'Módulos'!$I$2:$I$2464,"ATIVO") -> 205 | L28: Módulos operando | M28: Planilha | N28: Telemetria II | O28: Fidelizar | P28: Capacitação em Desenvolvimento | Q28: Em POC | R28: 46218
A29: PLENA | B29: Proposta comercial | C29: Faturamento inativo | D29: Guilherme | E29: =IF(OR($B29="POC Sem Evolução",$B29="Prospecção Sem Sucesso",$B29="Inativo",$B29="Prospecção"), "⚪ Sem dados",IF($C29="Faturando",IF($Q29="Com evolução","🟢 Saudável",IF($Q29="Sem evolução", "🟡 Atenção",IF(AND($P29="Capacitação Efetiva",$L29="Módulos operando"),"🟢 Saudável","🟡 Atenção"))), IF(AND($B29="Ativo",$C29="Faturamento inativo"),"🔴 Risco",IF($C29="","⚪ Sem dados","🟡 Atenção")))) -> 🟡 Atenção | F29: 42.722.360/0004-90 | G29: Bruno | H29: (32) 99912-5086 | I29: bruno.nascimento@grupomysa.com.br | J29: 46075 | K29: =COUNTIFS('Módulos'!$G$2:$G$2464,A29,'Módulos'!$I$2:$I$2464,"ATIVO") -> 6 | L29: Módulos operando | M29: Sascar | N29: Telemetria II | O29: Fidelizar | P29: Realizar Capacitação | Q29: Em POC | R29: 46210
A30: PORTINARI | B30: Inativo | C30: Faturamento inativo | D30: Guilherme | E30: =IF(OR($B30="POC Sem Evolução",$B30="Prospecção Sem Sucesso",$B30="Inativo",$B30="Prospecção"), "⚪ Sem dados",IF($C30="Faturando",IF($Q30="Com evolução","🟢 Saudável",IF($Q30="Sem evolução", "🟡 Atenção",IF(AND($P30="Capacitação Efetiva",$L30="Módulos operando"),"🟢 Saudável","🟡 Atenção"))), IF(AND($B30="Ativo",$C30="Faturamento inativo"),"🔴 Risco",IF($C30="","⚪ Sem dados","🟡 Atenção")))) -> ⚪ Sem dados | F30: 06.871.927/0001-83 | G30: Warlen | H30: (31) 99942-4685 | I30: comercial@portinaritransportes.com.br | J30: 45955 | K30: =COUNTIFS('Módulos'!$G$2:$G$2464,A30,'Módulos'!$I$2:$I$2464,"ATIVO") -> 7 | L30: Módulos operando | M30: Inoprime | N30: Telemetria II | O30: Fidelidade 12 meses | P30: Inativado | Q30: Inativado | R30: 46216
A31: R&M | B31: Ativo | C31: Faturando | D31: Diego | E31: =IF(OR($B31="POC Sem Evolução",$B31="Prospecção Sem Sucesso",$B31="Inativo",$B31="Prospecção"), "⚪ Sem dados",IF($C31="Faturando",IF($Q31="Com evolução","🟢 Saudável",IF($Q31="Sem evolução", "🟡 Atenção",IF(AND($P31="Capacitação Efetiva",$L31="Módulos operando"),"🟢 Saudável","🟡 Atenção"))), IF(AND($B31="Ativo",$C31="Faturamento inativo"),"🔴 Risco",IF($C31="","⚪ Sem dados","🟡 Atenção")))) -> 🟢 Saudável | F31: 42.883.904/0001-52 | G31: Rafael | H31: (31) 99961-1008 | I31: rafael.morais@lenarge.com.br | J31: 45901 | K31: =COUNTIFS('Módulos'!$G$2:$G$2464,A31,'Módulos'!$I$2:$I$2464,"ATIVO") -> 4 | L31: Módulos operando | M31: Sem dados | N31: Telemetria II | O31: Fidelidade 12 meses | P31: Capacitação Efetiva | Q31: Com evolução
A32: RLR | B32: Ativo | C32: Faturando | D32: Guilherme | E32: =IF(OR($B32="POC Sem Evolução",$B32="Prospecção Sem Sucesso",$B32="Inativo",$B32="Prospecção"), "⚪ Sem dados",IF($C32="Faturando",IF($Q32="Com evolução","🟢 Saudável",IF($Q32="Sem evolução", "🟡 Atenção",IF(AND($P32="Capacitação Efetiva",$L32="Módulos operando"),"🟢 Saudável","🟡 Atenção"))), IF(AND($B32="Ativo",$C32="Faturamento inativo"),"🔴 Risco",IF($C32="","⚪ Sem dados","🟡 Atenção")))) -> 🟢 Saudável | F32: 08.191.899/0001-89 | G32: Laura | H32: (31)97223-1004 | I32: fiscal@rlrtransporte.com.br | J32: 45809 | K32: =COUNTIFS('Módulos'!$G$2:$G$2464,A32,'Módulos'!$I$2:$I$2464,"ATIVO") -> 80 | L32: Módulos operando | M32: Sem dados | N32: Telemetria I | O32: Sem fidelidade | P32: Capacitação Efetiva | Q32: Com evolução
A33: RODEIRO | B33: Inativo | C33: Faturamento inativo | D33: Guilherme | E33: =IF(OR($B33="POC Sem Evolução",$B33="Prospecção Sem Sucesso",$B33="Inativo",$B33="Prospecção"), "⚪ Sem dados",IF($C33="Faturando",IF($Q33="Com evolução","🟢 Saudável",IF($Q33="Sem evolução", "🟡 Atenção",IF(AND($P33="Capacitação Efetiva",$L33="Módulos operando"),"🟢 Saudável","🟡 Atenção"))), IF(AND($B33="Ativo",$C33="Faturamento inativo"),"🔴 Risco",IF($C33="","⚪ Sem dados","🟡 Atenção")))) -> ⚪ Sem dados | F33: - | G33: - | H33: - | I33: - | K33: =COUNTIFS('Módulos'!$G$2:$G$2464,A33,'Módulos'!$I$2:$I$2464,"ATIVO") -> 0 | L33: Telemetria suspensa | M33: Sem dados | N33: Sem acesso | O33: Sem fidelidade | P33: Inativado | Q33: Inativado
A34: SATEL | B34: Prospecção sem Sucesso | C34: Faturamento inativo | D34: Guilherme | E34: =IF(OR($B34="POC Sem Evolução",$B34="Prospecção Sem Sucesso",$B34="Inativo",$B34="Prospecção"), "⚪ Sem dados",IF($C34="Faturando",IF($Q34="Com evolução","🟢 Saudável",IF($Q34="Sem evolução", "🟡 Atenção",IF(AND($P34="Capacitação Efetiva",$L34="Módulos operando"),"🟢 Saudável","🟡 Atenção"))), IF(AND($B34="Ativo",$C34="Faturamento inativo"),"🔴 Risco",IF($C34="","⚪ Sem dados","🟡 Atenção")))) -> ⚪ Sem dados | F34: - | G34: - | H34: - | I34: - | K34: =COUNTIFS('Módulos'!$G$2:$G$2464,A34,'Módulos'!$I$2:$I$2464,"ATIVO") -> 0 | L34: Telemetria suspensa | M34: Sem dados | N34: Sem acesso | O34: Fidelizar | P34: Inativado | Q34: Inativado
A35: SEMPRE VOLTA | B35: Ativo | C35: Faturando | D35: Diego | E35: =IF(OR($B35="POC Sem Evolução",$B35="Prospecção Sem Sucesso",$B35="Inativo",$B35="Prospecção"), "⚪ Sem dados",IF($C35="Faturando",IF($Q35="Com evolução","🟢 Saudável",IF($Q35="Sem evolução", "🟡 Atenção",IF(AND($P35="Capacitação Efetiva",$L35="Módulos operando"),"🟢 Saudável","🟡 Atenção"))), IF(AND($B35="Ativo",$C35="Faturamento inativo"),"🔴 Risco",IF($C35="","⚪ Sem dados","🟡 Atenção")))) -> 🟢 Saudável | F35: 20.786.711/0001-40 | G35: Brenda | H35: (31) 99898-1729 | I35: qualidade@semprevolta.net.br | J35: 46103 | K35: =COUNTIFS('Módulos'!$G$2:$G$2464,A35,'Módulos'!$I$2:$I$2464,"ATIVO") -> 33 | L35: Módulos operando | M35: Diário de Bordo | N35: Telemetria II | O35: Fidelidade 12 meses | P35: Capacitação Efetiva | Q35: Com evolução | R35: 46223
A36: TRANSFAL | B36: Prospecção sem Sucesso | C36: Faturamento inativo | E36: =IF(OR($B36="POC Sem Evolução",$B36="Prospecção Sem Sucesso",$B36="Inativo",$B36="Prospecção"), "⚪ Sem dados",IF($C36="Faturando",IF($Q36="Com evolução","🟢 Saudável",IF($Q36="Sem evolução", "🟡 Atenção",IF(AND($P36="Capacitação Efetiva",$L36="Módulos operando"),"🟢 Saudável","🟡 Atenção"))), IF(AND($B36="Ativo",$C36="Faturamento inativo"),"🔴 Risco",IF($C36="","⚪ Sem dados","🟡 Atenção")))) -> ⚪ Sem dados | K36: =COUNTIFS('Módulos'!$G$2:$G$2464,A36,'Módulos'!$I$2:$I$2464,"ATIVO") -> 0 | L36: Telemetria suspensa | M36: Sem dados | N36: Sem acesso | O36: Fidelizar | P36: Inativado | Q36: Inativado
A37: TRANSNIEL | B37: Prospecção | C37: Faturamento inativo | D37: Guilherme | E37: =IF(OR($B37="POC Sem Evolução",$B37="Prospecção Sem Sucesso",$B37="Inativo",$B37="Prospecção"), "⚪ Sem dados",IF($C37="Faturando",IF($Q37="Com evolução","🟢 Saudável",IF($Q37="Sem evolução", "🟡 Atenção",IF(AND($P37="Capacitação Efetiva",$L37="Módulos operando"),"🟢 Saudável","🟡 Atenção"))), IF(AND($B37="Ativo",$C37="Faturamento inativo"),"🔴 Risco",IF($C37="","⚪ Sem dados","🟡 Atenção")))) -> ⚪ Sem dados | F37: - | G37: - | H37: - | I37: - | K37: =COUNTIFS('Módulos'!$G$2:$G$2464,A37,'Módulos'!$I$2:$I$2464,"ATIVO") -> 0 | L37: Checar módulos | M37: Sem dados | N37: Sem acesso | O37: Sem fidelidade | P37: Realizar Capacitação | Q37: Sem dados | R37: 46217
A38: TRANSPORTADORA IRMÃOS GOMES | B38: Prospecção | C38: Faturamento inativo | D38: Diego | E38: =IF(OR($B38="POC Sem Evolução",$B38="Prospecção Sem Sucesso",$B38="Inativo",$B38="Prospecção"), "⚪ Sem dados",IF($C38="Faturando",IF($Q38="Com evolução","🟢 Saudável",IF($Q38="Sem evolução", "🟡 Atenção",IF(AND($P38="Capacitação Efetiva",$L38="Módulos operando"),"🟢 Saudável","🟡 Atenção"))), IF(AND($B38="Ativo",$C38="Faturamento inativo"),"🔴 Risco",IF($C38="","⚪ Sem dados","🟡 Atenção")))) -> ⚪ Sem dados | F38: - | G38: - | H38: - | I38: - | K38: =COUNTIFS('Módulos'!$G$2:$G$2464,A38,'Módulos'!$I$2:$I$2464,"ATIVO") -> 0 | L38: Checar módulos | M38: Sem dados | N38: Sem acesso | O38: Sem fidelidade | P38: Realizar Capacitação | Q38: Sem dados
A39: TRANSPORTADORA NOVA ERA | B39: POC Sem Evolução | C39: Faturamento inativo | D39: Diego | E39: =IF(OR($B39="POC Sem Evolução",$B39="Prospecção Sem Sucesso",$B39="Inativo",$B39="Prospecção"), "⚪ Sem dados",IF($C39="Faturando",IF($Q39="Com evolução","🟢 Saudável",IF($Q39="Sem evolução", "🟡 Atenção",IF(AND($P39="Capacitação Efetiva",$L39="Módulos operando"),"🟢 Saudável","🟡 Atenção"))), IF(AND($B39="Ativo",$C39="Faturamento inativo"),"🔴 Risco",IF($C39="","⚪ Sem dados","🟡 Atenção")))) -> ⚪ Sem dados | F39: 00.103.768/0001-90 | G39: Afranio | H39: (31) 99492-0164 | I39: afraniocaetano@transportesnovaera.com.br | J39: 46162 | K39: =COUNTIFS('Módulos'!$G$2:$G$2464,A39,'Módulos'!$I$2:$I$2464,"ATIVO") -> 0 | L39: Telemetria suspensa | M39: Maxtrack | N39: Sem acesso | O39: Fidelizar | P39: Inativado | Q39: Inativado
A40: TRANSKOMPA | B40: POC Sem Evolução | C40: Faturamento inativo | D40: Guilherme | E40: =IF(OR($B40="POC Sem Evolução",$B40="Prospecção Sem Sucesso",$B40="Inativo",$B40="Prospecção"), "⚪ Sem dados",IF($C40="Faturando",IF($Q40="Com evolução","🟢 Saudável",IF($Q40="Sem evolução", "🟡 Atenção",IF(AND($P40="Capacitação Efetiva",$L40="Módulos operando"),"🟢 Saudável","🟡 Atenção"))), IF(AND($B40="Ativo",$C40="Faturamento inativo"),"🔴 Risco",IF($C40="","⚪ Sem dados","🟡 Atenção")))) -> ⚪ Sem dados | F40: 65.311.235/0001-40 | G40: Adelson | H40: (11) 96377-7218 | I40: adelson.sena@transkompa.com.br | J40: 45901 | K40: =COUNTIFS('Módulos'!$G$2:$G$2464,A40,'Módulos'!$I$2:$I$2464,"ATIVO") -> 13 | L40: Módulos operando | M40: Boreal | N40: Sem acesso | O40: Fidelizar | P40: Inativado | Q40: Inativado | R40: 46219
A41: TRANSMOREIRA | B41: Período de teste | C41: Faturamento inativo | D41: Guilherme | E41: =IF(OR($B41="POC Sem Evolução",$B41="Prospecção Sem Sucesso",$B41="Inativo",$B41="Prospecção"), "⚪ Sem dados",IF($C41="Faturando",IF($Q41="Com evolução","🟢 Saudável",IF($Q41="Sem evolução", "🟡 Atenção",IF(AND($P41="Capacitação Efetiva",$L41="Módulos operando"),"🟢 Saudável","🟡 Atenção"))), IF(AND($B41="Ativo",$C41="Faturamento inativo"),"🔴 Risco",IF($C41="","⚪ Sem dados","🟡 Atenção")))) -> 🟡 Atenção | F41: 23.266.026/0001-81 | G41: - | H41: - | I41: - | J41: 45971 | K41: =COUNTIFS('Módulos'!$G$2:$G$2464,A41,'Módulos'!$I$2:$I$2464,"ATIVO") -> 10 | L41: Módulos operando | M41: Sem dados | N41: Telemetria II | O41: Fidelizar | P41: Realizar Capacitação | Q41: Em POC
A42: TRANSODILON | B42: Prospecção | C42: Faturamento inativo | D42: Guilherme | E42: =IF(OR($B42="POC Sem Evolução",$B42="Prospecção Sem Sucesso",$B42="Inativo",$B42="Prospecção"), "⚪ Sem dados",IF($C42="Faturando",IF($Q42="Com evolução","🟢 Saudável",IF($Q42="Sem evolução", "🟡 Atenção",IF(AND($P42="Capacitação Efetiva",$L42="Módulos operando"),"🟢 Saudável","🟡 Atenção"))), IF(AND($B42="Ativo",$C42="Faturamento inativo"),"🔴 Risco",IF($C42="","⚪ Sem dados","🟡 Atenção")))) -> ⚪ Sem dados | F42: 02.018.942/0001-22 | G42: Igor | H42: (31) 99986-1643 | I42: igor@transodilon.com.br | K42: =COUNTIFS('Módulos'!$G$2:$G$2464,A42,'Módulos'!$I$2:$I$2464,"ATIVO") -> 0 | L42: Checar módulos | M42: Sem dados | N42: Sem acesso | O42: Fidelizar | P42: Realizar Capacitação | Q42: Sem dados | R42: 46227
A43: TRANSPANORAMA | B43: POC Sem Evolução | C43: Faturamento inativo | D43: Guilherme | E43: =IF(OR($B43="POC Sem Evolução",$B43="Prospecção Sem Sucesso",$B43="Inativo",$B43="Prospecção"), "⚪ Sem dados",IF($C43="Faturando",IF($Q43="Com evolução","🟢 Saudável",IF($Q43="Sem evolução", "🟡 Atenção",IF(AND($P43="Capacitação Efetiva",$L43="Módulos operando"),"🟢 Saudável","🟡 Atenção"))), IF(AND($B43="Ativo",$C43="Faturamento inativo"),"🔴 Risco",IF($C43="","⚪ Sem dados","🟡 Atenção")))) -> ⚪ Sem dados | F43: - | G43: - | H43: - | I43: - | K43: =COUNTIFS('Módulos'!$G$2:$G$2464,A43,'Módulos'!$I$2:$I$2464,"ATIVO") -> 0 | L43: Telemetria suspensa | M43: Sem dados | N43: Sem acesso | O43: Sem fidelidade | P43: Inativado | Q43: Inativado
A44: TSA | B44: POC Sem Evolução | C44: Faturamento inativo | D44: Guilherme | E44: =IF(OR($B44="POC Sem Evolução",$B44="Prospecção Sem Sucesso",$B44="Inativo",$B44="Prospecção"), "⚪ Sem dados",IF($C44="Faturando",IF($Q44="Com evolução","🟢 Saudável",IF($Q44="Sem evolução", "🟡 Atenção",IF(AND($P44="Capacitação Efetiva",$L44="Módulos operando"),"🟢 Saudável","🟡 Atenção"))), IF(AND($B44="Ativo",$C44="Faturamento inativo"),"🔴 Risco",IF($C44="","⚪ Sem dados","🟡 Atenção")))) -> ⚪ Sem dados | F44: - | G44: - | H44: - | I44: - | K44: =COUNTIFS('Módulos'!$G$2:$G$2464,A44,'Módulos'!$I$2:$I$2464,"ATIVO") -> 0 | L44: Telemetria suspensa | M44: Sem dados | N44: Sem acesso | O44: Sem fidelidade | P44: Inativado | Q44: Inativado
A45: VALLENCE | B45: Ativo | C45: Faturando | D45: Diego | E45: =IF(OR($B45="POC Sem Evolução",$B45="Prospecção Sem Sucesso",$B45="Inativo",$B45="Prospecção"), "⚪ Sem dados",IF($C45="Faturando",IF($Q45="Com evolução","🟢 Saudável",IF($Q45="Sem evolução", "🟡 Atenção",IF(AND($P45="Capacitação Efetiva",$L45="Módulos operando"),"🟢 Saudável","🟡 Atenção"))), IF(AND($B45="Ativo",$C45="Faturamento inativo"),"🔴 Risco",IF($C45="","⚪ Sem dados","🟡 Atenção")))) -> 🟡 Atenção | F45: 08.413.139/0001-79 | G45: Flávio | H45: (31) 99629-1722 | I45: flavio@vallence.com.br | J45: 45931 | K45: =COUNTIFS('Módulos'!$G$2:$G$2464,A45,'Módulos'!$I$2:$I$2464,"ATIVO") -> 6 | L45: Módulos operando | M45: Não faz | N45: Telemetria II | O45: Sem fidelidade | P45: Capacitação Efetiva | Q45: Sem evolução | R45: 46223
A46: WD AGROINDUSTRIAL | B46: POC Sem Evolução | C46: Faturamento inativo | D46: Diego | E46: =IF(OR($B46="POC Sem Evolução",$B46="Prospecção Sem Sucesso",$B46="Inativo",$B46="Prospecção"), "⚪ Sem dados",IF($C46="Faturando",IF($Q46="Com evolução","🟢 Saudável",IF($Q46="Sem evolução", "🟡 Atenção",IF(AND($P46="Capacitação Efetiva",$L46="Módulos operando"),"🟢 Saudável","🟡 Atenção"))), IF(AND($B46="Ativo",$C46="Faturamento inativo"),"🔴 Risco",IF($C46="","⚪ Sem dados","🟡 Atenção")))) -> ⚪ Sem dados | F46: - | G46: - | H46: - | I46: - | J46: 45901 | K46: =COUNTIFS('Módulos'!$G$2:$G$2464,A46,'Módulos'!$I$2:$I$2464,"ATIVO") -> 5 | L46: Módulos operando | M46: Sem dados | N46: Sem acesso | O46: Fidelizar | P46: Realizar Capacitação | Q46: Em POC | R46: 46150
A47: ZERO CARBON | B47: Período de teste | C47: Faturamento inativo | D47: Guilherme | E47: =IF(OR($B47="POC Sem Evolução",$B47="Prospecção Sem Sucesso",$B47="Inativo",$B47="Prospecção"), "⚪ Sem dados",IF($C47="Faturando",IF($Q47="Com evolução","🟢 Saudável",IF($Q47="Sem evolução", "🟡 Atenção",IF(AND($P47="Capacitação Efetiva",$L47="Módulos operando"),"🟢 Saudável","🟡 Atenção"))), IF(AND($B47="Ativo",$C47="Faturamento inativo"),"🔴 Risco",IF($C47="","⚪ Sem dados","🟡 Atenção")))) -> 🟡 Atenção | F47: 21.545.694/0001-12 | G47: Luciene | H47: (31) 99199-5306 | I47: luciene.carvalho@zerocarbongroup.com | J47: 46126 | K47: =COUNTIFS('Módulos'!$G$2:$G$2464,A47,'Módulos'!$I$2:$I$2464,"ATIVO") -> 2 | L47: Módulos operando | M47: Sascar | N47: Telemetria II | O47: Fidelizar | P47: Realizar Capacitação | Q47: Em POC | R47: 46204

Sheet Pipeline
A1: Prioridade | B1: Empresa | C1: Segmento | D1: UF/Região | E1: Nº veíc. (est.) | F1: Decisor-alvo | G1: Canal | H1: Estágio | I1: Próxima ação | J1: Data próx. ação | K1: Valor ponderado | L1: Dor / Gancho | M1: Observações
A2: A | B2: Expresso Alvorada | C2: Granel sólido (cimento/siderurgia/coque) | D2: MG | F2: Diretor de Operações / Dono | G2: Indicação | H2: Lead | I2: Diagnóstico de risco Lei 13.103 | K2: {=IFERROR($E2*Config!$P$2*INDEX(Config!$K$3:$K$10,MATCH($H2,Config!$J$3:$J$10,0)),0)} -> 0 | L2: Espelho da Aperam; já usa rastreamento satelital
A3: A | B3: GT Minas Transportes | C3: Granel / container | D3: Varginha-MG | F3: Gestor de Frota | G3: Outbound LinkedIn | H3: Lead | I3: Enviar diagnóstico gratuito | K3: {=IFERROR($E3*Config!$P$2*INDEX(Config!$K$3:$K$10,MATCH($H3,Config!$J$3:$J$10,0)),0)} -> 0 | L3: Frota 100% rastreada, mid-market MG
A4: A | B4: Transportes Faraem | C4: Graneleiro (Sul/Sudeste) | D4: RS/SC | F4: Diretor de Operações | G4: Outbound e-mail | H4: Lead | I4: Calculadora ROI diesel | K4: {=IFERROR($E4*Config!$P$2*INDEX(Config!$K$3:$K$10,MATCH($H4,Config!$J$3:$J$10,0)),0)} -> 0 | L4: Graneleiro longa distância
A5: A | B5: Sada Transportes | C5: Cegonha / siderurgia | D5: Betim-MG | F5: Diretor de Operações | G5: Indicação | H5: Lead | I5: Case Aperam mesma região | K5: {=IFERROR($E5*Config!$P$2*INDEX(Config!$K$3:$K$10,MATCH($H5,Config!$J$3:$J$10,0)),0)} -> 0 | L5: Peer siderúrgico da Aperam
A6: A | B6: Transpanorama | C6: Granel líquido / químico | D6: RS | F6: COO | G6: Outbound LinkedIn | H6: Lead | I6: Diagnóstico de jornada (carga perigosa) | K6: {=IFERROR($E6*Config!$P$2*INDEX(Config!$K$3:$K$10,MATCH($H6,Config!$J$3:$J$10,0)),0)} -> 0 | L6: Longa distância + carga perigosa
A7: A | B7: Expresso Nepomuceno | C7: Carga geral longa distância | D7: Três Corações-MG | F7: Diretor / Dono | G7: Indicação | H7: Lead | I7: Pedir indicação via cliente MG | K7: {=IFERROR($E7*Config!$P$2*INDEX(Config!$K$3:$K$10,MATCH($H7,Config!$J$3:$J$10,0)),0)} -> 0 | L7: Tradicional MG, frota própria
A8: A | B8: Del Rey Transportes | C8: Carga geral | D8: BH-MG | F8: Dono / Diretor | G8: Outbound LinkedIn | H8: Lead | I8: One-pager compliance + demo | K8: {=IFERROR($E8*Config!$P$2*INDEX(Config!$K$3:$K$10,MATCH($H8,Config!$J$3:$J$10,0)),0)} -> 0 | L8: Mid-market MG
A9: A | B9: Transmathias Transportes | C9: Carga / granel | D9: MG | F9: Dono / Gestor de Frota | G9: Indicação | H9: Lead | I9: Diagnóstico + indicação regional | K9: {=IFERROR($E9*Config!$P$2*INDEX(Config!$K$3:$K$10,MATCH($H9,Config!$J$3:$J$10,0)),0)} -> 0 | L9: Mid-market MG
A10: A | B10: Tora Transportes | C10: Granel sólido longa distância | D10: Nacional | F10: Diretor de Operações | G10: Outbound e-mail | H10: Lead | I10: ROI por veículo | K10: {=IFERROR($E10*Config!$P$2*INDEX(Config!$K$3:$K$10,MATCH($H10,Config!$J$3:$J$10,0)),0)} -> 0 | L10: Alto consumo diesel
A11: A | B11: Rodovale / Rodocap | C11: Granel / carga | D11: MG / interior | F11: Gestor de Frota | G11: Outbound LinkedIn | H11: Lead | I11: Calculadora de ROI | K11: {=IFERROR($E11*Config!$P$2*INDEX(Config!$K$3:$K$10,MATCH($H11,Config!$J$3:$J$10,0)),0)} -> 0 | L11: Graneleiro mid-market
A12: B | B12: Cooxupé | C12: Cooperativa de café | D12: Guaxupé-MG/SP | F12: Diretor de Logística | G12: Evento | H12: Lead | I12: Assessment de safra + case MG | K12: {=IFERROR($E12*Config!$P$2*INDEX(Config!$K$3:$K$10,MATCH($H12,Config!$J$3:$J$10,0)),0)} -> 0 | L12: Coop MG (quintal), pico de safra
A13: B | B13: Coamo | C13: Cooperativa agro (grãos) | D13: Campo Mourão-PR | F13: Diretor de Logística | G13: Evento | H13: Lead | I13: Assessment safra + case Coopervale | K13: {=IFERROR($E13*Config!$P$2*INDEX(Config!$K$3:$K$10,MATCH($H13,Config!$J$3:$J$10,0)),0)} -> 0 | L13: Frota própria grande
... A25: C | B25: JBS / Marfrig / Aurora | C25: Frigorífico / proteína | D25: Nacional / Sul | F25: Gerente de Logística regional | G25: Indicação | H25: Lead | I25: Dor de perecível parado | K25: {=IFERROR($E25*Config!$P$2*INDEX(Config!$K$3:$K$10,MATCH($H25,Config!$J$3:$J$10,0)),0)} -> 0 | L25: Frota frigorificada própria

Sheet Controle de OS
A1: Nº DA OS | B1: STATUS | C1: QUEM ABRIU | D1: EMPRESA | E1: SOLICITANTE | F1: CONTATO | G1: DATA | H1: HORA | I1: CRITICIDADE | J1: ANALISTA | K1: PRODUTO/SERVIÇO | L1: DESCRIÇÃO DA DEMANDA | M1: PLACA | N1: SLA (Objetivo) | O1: VENCIMENTO | P1: SOLUÇÃO/COMENTÁRIOS/EVOLUÇÃO | Q1: CONCLUSÃO
A2: 2026000001 | B2: FINALIZADO | C2: MARLON | D2: M1 | E2: Deivson Figueredo | G2: 46027 | H2: 0 | I2: ATENDIDO | J2: MARLON | K2: SUPORTE | L2: Relatório de rastreio | M2: TCR3G73 | N2: 46027 | O2: =IF(N2="","SEM DATA APONTADA",(IF(B2="FINALIZADO", "CONCLUÍDO",(IF(B2="ANALISADO", "ANALISADO",IF(N2<TODAY(), "VENCIDO", IF(N2=TODAY(), "VENCE HOJE", IF(N2<=TODAY()+5,"VENCENDO", "NO PRAZO")))))))) -> CONCLUÍDO | P2: Enviei o relatorio | Q2: 46027
A3: 2026000002 | B3: FINALIZADO | C3: MARLON | D3: LENARGE | E3: Gabriel Felipe Viana da Silva | G3: 46027 | H3: 0 | I3: ATENDIDO | J3: MARLON | K3: SUPORTE | L3: Disponibilizar acesso ao APP LENARGE | N3: 46027 | O3: =IF(N3="","SEM DATA APONTADA",(IF(B3="FINALIZADO", "CONCLUÍDO",(IF(B3="ANALISADO", "ANALISADO",IF(N3<TODAY(), "VENCIDO", IF(N3=TODAY(), "VENCE HOJE", IF(N3<=TODAY()+5,"VENCENDO", "NO PRAZO")))))))) -> CONCLUÍDO | P3: Acesso ao APP Lenarge concedido. | Q3: 46027
A4: 2026000003 | B4: FINALIZADO | C4: MARLON | D4: LENARGE | E4: Gabriel Fernandes inacio | G4: 46027 | H4: 0 | I4: ATENDIDO | J4: MARLON | K4: SUPORTE | L4: Lentidão generalizada no App Lenarge | N4: 46027 | O4: =IF(N4="","SEM DATA APONTADA",(IF(B4="FINALIZADO", "CONCLUÍDO",(IF(B4="ANALISADO", "ANALISADO",IF(N4<TODAY(), "VENCIDO", IF(N4=TODAY(), "VENCE HOJE", IF(N4<=TODAY()+5,"VENCENDO", "NO PRAZO")))))))) -> CONCLUÍDO | Q4: =N4 -> 46027
A5: 2026000004 | B5: FINALIZADO | C5: MARLON | D5: DNA | E5: Deivson Figueredo | G5: 46027 | H5: 0 | I5: ATENDIDO | J5: MARLON | K5: TELEMETRIA | L5: Veiculos não estão reportando no tracking | M5: QUX9C89 | N5: 46028 | O5: =IF(N5="","SEM DATA APONTADA",(IF(B5="FINALIZADO", "CONCLUÍDO",(IF(B5="ANALISADO", "ANALISADO",IF(N5<TODAY(), "VENCIDO", IF(N5=TODAY(), "VENCE HOJE", IF(N5<=TODAY()+5,"VENCENDO", "NO PRAZO")))))))) -> CONCLUÍDO | P5: Enviei a config | Q5: 46028
B6: FINALIZADO | D6: DNA | H6: 0 | I6: ATENDIDO | J6: MARLON | K6: TELEMETRIA | M6: QOL5H74 | N6: 46028 | O6: =IF(N6="","SEM DATA APONTADA",(IF(B6="FINALIZADO", "CONCLUÍDO",(IF(B6="ANALISADO", "ANALISADO",IF(N6<TODAY(), "VENCIDO", IF(N6=TODAY(), "VENCE HOJE", IF(N6<=TODAY()+5,"VENCENDO", "NO PRAZO")))))))) -> CONCLUÍDO | P6: Enviei a config | Q6: 46028
B7: FINALIZADO | D7: DNA | H7: 0 | I7: ATENDIDO | J7: MARLON | K7: TELEMETRIA | M7: QPQ2J79 | N7: 46028 | O7: =IF(N7="","SEM DATA APONTADA",(IF(B7="FINALIZADO", "CONCLUÍDO",(IF(B7="ANALISADO", "ANALISADO",IF(N7<TODAY(), "VENCIDO", IF(N7=TODAY(), "VENCE HOJE", IF(N7<=TODAY()+5,"VENCENDO", "NO PRAZO")))))))) -> CONCLUÍDO | P7: Enviei a config | Q7: 46028
B8: FINALIZADO | D8: DNA | H8: 0 | I8: ATENDIDO | J8: MARLON | K8: TELEMETRIA | M8: QMT4G46 | N8: 46028 | O8: =IF(N8="","SEM DATA APONTADA",(IF(B8="FINALIZADO", "CONCLUÍDO",(IF(B8="ANALISADO", "ANALISADO",IF(N8<TODAY(), "VENCIDO", IF(N8=TODAY(), "VENCE HOJE", IF(N8<=TODAY()+5,"VENCENDO", "NO PRAZO")))))))) -> CONCLUÍDO | P8: Enviei a config | Q8: 46028
B9: FINALIZADO | D9: DNA | H9: 0 | I9: ATENDIDO | J9: MARLON | K9: TELEMETRIA | M9: RNU5H15 | N9: 46028 | O9: =IF(N9="","SEM DATA APONTADA",(IF(B9="FINALIZADO", "CONCLUÍDO",(IF(B9="ANALISADO", "ANALISADO",IF(N9<TODAY(), "VENCIDO", IF(N9=TODAY(), "VENCE HOJE", IF(N9<=TODAY()+5,"VENCENDO", "NO PRAZO")))))))) -> CONCLUÍDO | P9: Enviei a config | Q9: 46028
A10: 2026000005 | B10: FINALIZADO | C10: MARLON | D10: LENARGE | E10: Maria Vieira | G10: 46027 | H10: 0 | I10: ATENDIDO | J10: PABLO | K10: TORRE | L10: Disponibilizar acesso ao APP LENARGE e liberação de permissão a funcionalidade de troca de motorista | N10: 46027 | O10: =IF(N10="","SEM DATA APONTADA",(IF(B10="FINALIZADO", "CONCLUÍDO",(IF(B10="ANALISADO", "ANALISADO",IF(N10<TODAY(), "VENCIDO", IF(N10=TODAY(), "VENCE HOJE", IF(N10<=TODAY()+5,"VENCENDO", "NO PRAZO")))))))) -> CONCLUÍDO | P10: Acesso ao APP Lenarge concedido e permissão para troca de motorista liberada. | Q10: 46027
A11: 2026000006 | B11: FINALIZADO | C11: MARLON | D11: LENARGE | E11: Letícia Cristina | G11: 46027 | H11: 0 | I11: ATENDIDO | J11: MARLON | K11: SUPORTE | L11: Falha freios / Falha elétrica / Perda de funcionalidade / Tacógrafo com defeito / Funcionalidade transmissão reduzida. | M11: RBE9D16 | N11: 46027 | O11: =IF(N11="","SEM DATA APONTADA",(IF(B11="FINALIZADO", "CONCLUÍDO",(IF(B11="ANALISADO", "ANALISADO",IF(N11<TODAY(), "VENCIDO", IF(N11=TODAY(), "VENCE HOJE", IF(N11<=TODAY()+5,"VENCENDO", "NO PRAZO")))))))) -> CONCLUÍDO | P11: Enviei a config | Q11: 46027
A12: 2026000007 | B12: FINALIZADO | C12: MARLON | D12: LENARGE | E12: Vinicius Moraes | G12: 46025 | H12: 0 | I12: ATENDIDO | J12: PABLO | K12: TORRE | L12: Autorização de perimissão a trocca de motorista | N12: 46027 | O12: =IF(N12="","SEM DATA APONTADA",(IF(B12="FINALIZADO", "CONCLUÍDO",(IF(B12="ANALISADO", "ANALISADO",IF(N12<TODAY(), "VENCIDO", IF(N12=TODAY(), "VENCE HOJE", IF(N12<=TODAY()+5,"VENCENDO", "NO PRAZO")))))))) -> CONCLUÍDO | P12: Permissão liberada apos aurotização do setor de faturamento (Juliana) | Q12: 46027
A13: 2026000008 | B13: FINALIZADO | C13: MARLON | D13: LENARGE | E13: João Machado | G13: 46027 | H13: 0 | I13: ATENDIDO | J13: PABLO | K13: TORRE | L13: Disponibilizar acesso ao APP LENARGE e liberação de permissão a funcionalidade de troca de motorista | N13: 46027 | O13: =IF(N13="","SEM DATA APONTADA",(IF(B13="FINALIZADO", "CONCLUÍDO",(IF(B13="ANALISADO", "ANALISADO",IF(N13<TODAY(), "VENCIDO", IF(N13=TODAY(), "VENCE HOJE", IF(N13<=TODAY()+5,"VENCENDO", "NO PRAZO")))))))) -> CONCLUÍDO | P13: Acesso ao APP Lenarge concedido e permissão para troca de motorista liberada. | Q13: 46027
A14: 2026000009 | B14: FINALIZADO | C14: MARLON | D14: M1 | E14: Deivson Figueredo | G14: 46027 | H14: 0 | I14: ATENDIDO | J14: MARLON | K14: SUPORTE | L14: Auxilio para emitir relatório de premiação | N14: 46027 | O14: =IF(N14="","SEM DATA APONTADA",(IF(B14="FINALIZADO", "CONCLUÍDO",(IF(B14="ANALISADO", "ANALISADO",IF(N14<TODAY(), "VENCIDO", IF(N14=TODAY(), "VENCE HOJE", IF(N14<=TODAY()+5,"VENCENDO", "NO PRAZO")))))))) -> CONCLUÍDO | P14: Usuário orientado quanto ao procedimento correto para emissão do relatório de premiação no sistema, com sucesso. | Q14: 46027
A15: 2026000010 | B15: FINALIZADO | C15: MARLON | D15: LENARGE | E15: João Machado | G15: 46027 | H15: 0 | I15: ATENDIDO | J15: MARLON | K15: SUPORTE | L15: Atualizar app Betruck no Knox | N15: 46027 | O15: =IF(N15="","SEM DATA APONTADA",(IF(B15="FINALIZADO", "CONCLUÍDO",(IF(B15="ANALISADO", "ANALISADO",IF(N15<TODAY(), "VENCIDO", IF(N15=TODAY(), "VENCE HOJE", IF(N15<=TODAY()+5,"VENCENDO", "NO PRAZO")))))))) -> CONCLUÍDO | P15: App foi atualizado | Q15: 46027
A16: 2026000011 | B16: FINALIZADO | C16: MARLON | D16: LENARGE | E16: Letícia Cristina | G16: 46027 | H16: 0 | I16: ATENDIDO | J16: MARLON | K16: SUPORTE | L16: Não está mostrando os comandos para o motorista | M16: RBE5G92 | N16: 46027 | O16: =IF(N16="","SEM DATA APONTADA",(IF(B16="FINALIZADO", "CONCLUÍDO",(IF(B16="ANALISADO", "ANALISADO",IF(N16<TODAY(), "VENCIDO", IF(N16=TODAY(), "VENCE HOJE", IF(N16<=TODAY()+5,"VENCENDO", "NO PRAZO")))))))) -> CONCLUÍDO | P16: Enviei a config | Q16: 46027
A17: 2026000012 | B17: FINALIZADO | C17: DIEGO | D17: FACSS | E17: Diego Sena | G17: 46027 | H17: 0 | I17: ATENDIDO | J17: MARLON | K17: SUPORTE | L17: Veiculos não estão reportando no tracking, Traccar e Dashboard | N17: 46031 | O17: =IF(N17="","SEM DATA APONTADA",(IF(B17="FINALIZADO", "CONCLUÍDO",(IF(B17="ANALISADO", "ANALISADO",IF(N17<TODAY(), "VENCIDO", IF(N17=TODAY(), "VENCE HOJE", IF(N17<=TODAY()+5,"VENCENDO", "NO PRAZO")))))))) -> CONCLUÍDO | P17: Solicitada a troca dos módulos, pois o reenvio da config não foi aplicado com sucesso e os veículos não voltaram a reportar. | Q17: 46028
A18: 2026000013 | B18: FINALIZADO | C18: MARLON | D18: FACSS | E18: Leonardo Branco | G18: 46027 | H18: 0 | I18: ATENDIDO | J18: MARLON | K18: SUPORTE | L18: Criar usuario para P&W | N18: 46027 | O18: =IF(N18="","SEM DATA APONTADA",(IF(B18="FINALIZADO", "CONCLUÍDO",(IF(B18="ANALISADO", "ANALISADO",IF(N18<TODAY(), "VENCIDO", IF(N18=TODAY(), "VENCE HOJE", IF(N18<=TODAY()+5,"VENCENDO", "NO PRAZO")))))))) -> CONCLUÍDO | P18: Usuario criado com sucesso. | Q18: 46027
A19: 2026000014 | B19: FINALIZADO | C19: MARLON | D19: LENARGE | E19: Walker Rodrigues | G19: 46028 | H19: 0 | I19: ATENDIDO | J19: PABLO | K19: TORRE | L19: Rastreador não funciona no app Lenarge. | N19: 46028 | O19: =IF(N19="","SEM DATA APONTADA",(IF(B19="FINALIZADO", "CONCLUÍDO",(IF(B19="ANALISADO", "ANALISADO",IF(N19<TODAY(), "VENCIDO", IF(N19=TODAY(), "VENCE HOJE", IF(N19<=TODAY()+5,"VENCENDO", "NO PRAZO")))))))) -> CONCLUÍDO | P19: Por falta de retorno do solicitante o chamado foiu encerrado. | Q19: 46028
A20: 2026000015 | B20: FINALIZADO | C20: DIEGO | D20: LENARGE | E20: Leandro Galdino | G20: 46028 | H20: 0 | I20: ATENDIDO | J20: DIEGO | K20: TELEMETRIA | L20: Veiculo não apresenta dados de telemetria | M20: RFZ4I84 | N20: 46028 | O20: =IF(N20="","SEM DATA APONTADA",(IF(B20="FINALIZADO", "CONCLUÍDO",(IF(B20="ANALISADO", "ANALISADO",IF(N20<TODAY(), "VENCIDO", IF(N20=TODAY(), "VENCE HOJE", IF(N20<=TODAY()+5,"VENCENDO", "NO PRAZO")))))))) -> CONCLUÍDO | P20: Será realizada a troca do módulo | Q20: 46028
A21: 2026000016 | B21: FINALIZADO | C21: MARLON | D21: APERAM Carvão | E21: Fernando Aristeu | G21: 46028 | H21: 0 | I21: ATENDIDO | J21: DIEGO | K21: SUPORTE | L21: Relatório completo de quilômetros rodados no mês de dezembro, bem como a quantidade de combustível consumida, discriminado por frota. | N21: 46028 | O21: =IF(N21="","SEM DATA APONTADA",(IF(B21="FINALIZADO", "CONCLUÍDO",(IF(B21="ANALISADO", "ANALISADO",IF(N21<TODAY(), "VENCIDO", IF(N21=TODAY(), "VENCE HOJE", IF(N21<=TODAY()+5,"VENCENDO", "NO PRAZO")))))))) -> CONCLUÍDO | P21: Relatório enviado. | Q21: 46028
A22: 2026000017 | B22: FINALIZADO | C22: MARLON | D22: LENARGE | E22: Leandro Galdino | G22: 46028 | H22: 0 | I22: ATENDIDO | J22: PABLO | K22: TORRE | L22: Veículo apresenta dados de telemetria apenas vinculados à placa e não ao motorista, impedindo que o motorista visualize suas informações de condução. | M22: RKR7J21 | N22: 46030 | O22: =IF(N22="","SEM DATA APONTADA",(IF(B22="FINALIZADO", "CONCLUÍDO",(IF(B22="ANALISADO", "ANALISADO",IF(N22<TODAY(), "VENCIDO", IF(N22=TODAY(), "VENCE HOJE", IF(N22<=TODAY()+5,"VENCENDO", "NO PRAZO")))))))) -> CONCLUÍDO | P22: Veículo identificado em manutenção, sem transmissão de sinal desde 09/01 às 18:06. Última localização registrada na concessionária DAF, indicando possível desligamento durante o processo de manutenção. Performance do motorista encontra-se normal. Possível falha ou desligamento do rastreador durante a manutenção. | Q22: 46037
A23: 2026000018 | B23: FINALIZADO | C23: MARLON | D23: LENARGE | E23: Amanda | G23: 46028 | H23: 0 | I23: ATENDIDO | J23: MARLON | K23: SUPORTE | L23: Criar usuario para funcionário do controle de manutenção | N23: 46028 | O23: =IF(N23="","SEM DATA APONTADA",(IF(B23="FINALIZADO", "CONCLUÍDO",(IF(B23="ANALISADO", "ANALISADO",IF(N23<TODAY(), "VENCIDO", IF(N23=TODAY(), "VENCE HOJE", IF(N23<=TODAY()+5,"VENCENDO", "NO PRAZO")))))))) -> CONCLUÍDO | P23: Usuario criado com sucesso. | Q23: 46028
A24: 2026000020 | B24: FINALIZADO | C24: DIEGO | D24: FACSS | E24: Diego Sena | G24: 46028 | H24: 0 | I24: ATENDIDO | J24: MARLON | K24: SUPORTE | L24: Veiculos não estão reportando no tracking, Traccar e Dashboard | N24: 46030 | O24: =IF(N24="","SEM DATA APONTADA",(IF(B24="FINALIZADO", "CONCLUÍDO",(IF(B24="ANALISADO", "ANALISADO",IF(N24<TODAY(), "VENCIDO", IF(N24=TODAY(), "VENCE HOJE", IF(N24<=TODAY()+5,"VENCENDO", "NO PRAZO")))))))) -> CONCLUÍDO | Q24: 46030
A25: 2026000021 | B25: FINALIZADO | C25: MARLON | D25: LENARGE | E25: Walker Rodrigues | G25: 46028 | H25: 0 | I25: ATENDIDO | J25: MARLON | K25: SUPORTE | L25: Falha no EBS | M25: TTR8H44 | N25: 46028 | O25: =IF(N25="","SEM DATA APONTADA",(IF(B25="FINALIZADO", "CONCLUÍDO",(IF(B25="ANALISADO", "ANALISADO",IF(N25<TODAY(), "VENCIDO", IF(N25=TODAY(), "VENCE HOJE", IF(N25<=TODAY()+5,"VENCENDO", "NO PRAZO")))))))) -> CONCLUÍDO | P25: Enviei a config | Q25: 46028
A26: 2026000022 | B26: FINALIZADO | C26: MARLON | D26: LENARGE | E26: Amanda | G26: 46028 | H26: 0 | I26: ATENDIDO | J26: MARLON | K26: SUPORTE | L26: Criar usuario para funcionário do controle de manutenção | N26: 46028 | O26: =IF(N26="","SEM DATA APONTADA",(IF(B26="FINALIZADO", "CONCLUÍDO",(IF(B26="ANALISADO", "ANALISADO",IF(N26<TODAY(), "VENCIDO", IF(N26=TODAY(), "VENCE HOJE", IF(N26<=TODAY()+5,"VENCENDO", "NO PRAZO")))))))) -> CONCLUÍDO | P26: Usuario criado com sucesso. | Q26: 46028
A27: 2026000023 | B27: FINALIZADO | C27: MARLON | D27: RLR | E27: Alessandro | G27: 45664 | H27: 0 | I27: ATENDIDO | J27: PABLO | K27: TORRE | L27: Veículo apresenta dados de telemetria apenas vinculados à placa e não ao motorista, impedindo que o motorista visualize suas informações de condução. | M27: TCU5I71 | N27: 46030 | O27: =IF(N27="","SEM DATA APONTADA",(IF(B27="FINALIZADO", "CONCLUÍDO",(IF(B27="ANALISADO", "ANALISADO",IF(N27<TODAY(), "VENCIDO", IF(N27=TODAY(), "VENCE HOJE", IF(N27<=TODAY()+5,"VENCENDO", "NO PRAZO")))))))) -> CONCLUÍDO | P27: Houve a troca do ID do motorista, o sistema voltará a reportar normalmente após a atualização realizada. | Q27: =N27 -> 46030
A28: 2026000024 | B28: FINALIZADO | C28: DIEGO | D28: LENARGE | E28: Breno Vinícius | G28: 45664 | H28: 0 | I28: ATENDIDO | J28: GABRIEL | K28: TELEMETRIA | L28: Veiculo não apresenta dados de telemetria | M28: TTR8H42 | N28: 46030 | O28: =IF(N28="","SEM DATA APONTADA",(IF(B28="FINALIZADO", "CONCLUÍDO",(IF(B28="ANALISADO", "ANALISADO",IF(N28<TODAY(), "VENCIDO", IF(N28=TODAY(), "VENCE HOJE", IF(N28<=TODAY()+5,"VENCENDO", "NO PRAZO")))))))) -> CONCLUÍDO | P28: Voltou a reportar no Dashboard. | Q28: 46034
A29: 2026000025 | B29: FINALIZADO | C29: MARLON | D29: LENARGE | E29: Jussara Sacramento | G29: 45664 | H29: 0 | I29: ATENDIDO | J29: PEDRO | K29: SUPORTE | L29: Telefone coorporativo sem internet | N29: 46029 | O29: =IF(N29="","SEM DATA APONTADA",(IF(B29="FINALIZADO", "CONCLUÍDO",(IF(B29="ANALISADO", "ANALISADO",IF(N29<TODAY(), "VENCIDO", IF(N29=TODAY(), "VENCE HOJE", IF(N29<=TODAY()+5,"VENCENDO", "NO PRAZO")))))))) -> CONCLUÍDO | P29: Reiniciado pelo Knox | Q29: 46029
A30: 2026000026 | B30: FINALIZADO | C30: MARLON | D30: LENARGE | E30: Salvador | G30: 46028 | H30: 0 | I30: ATENDIDO | J30: PABLO | K30: TORRE | L30: Veículo apresenta dados de telemetria apenas vinculados à placa e não ao motorista, impedindo que o motorista visualize suas informações de condução. | M30: TTB0J88 | N30: 46029 | O30: =IF(N30="","SEM DATA APONTADA",(IF(B30="FINALIZADO", "CONCLUÍDO",(IF(B30="ANALISADO", "ANALISADO",IF(N30<TODAY(), "VENCIDO", IF(N30=TODAY(), "VENCE HOJE", IF(N30<=TODAY()+5,"VENCENDO", "NO PRAZO")))))))) -> CONCLUÍDO | P30: Houve a troca do rastreador e realizamos a atualização para o ID do rastreador atual no sistema. | Q30: 07/012026
A31: 2026000027 | B31: FINALIZADO | C31: MARLON | D31: LENARGE | E31: Leandro Galdino | G31: 45664 | H31: 0 | I31: ATENDIDO | J31: GABRIEL | K31: TELEMETRIA | L31: Veículo não esta marcando a Inércia de forma correta | M31: SRM3D70 | N31: 46059 | O31: =IF(N31="","SEM DATA APONTADA",(IF(B31="FINALIZADO", "CONCLUÍDO",(IF(B31="ANALISADO", "ANALISADO",IF(N31<TODAY(), "VENCIDO", IF(N31=TODAY(), "VENCE HOJE", IF(N31<=TODAY()+5,"VENCENDO", "NO PRAZO")))))))) -> CONCLUÍDO | P31: A inicia desse veiculo foi resolvida, mas para a resolução ser definitiva é necessario passar essa alterção para o Torre de contole (A alteração feita foi retirar uma das validações que é feita para verificar se o veiculo esta em inecia, retiramos a validação do delta do speed maior que 0), também foi realizada a troca do módulo. | Q31: 46084
A32: 2026000028 | B32: FINALIZADO | C32: MARLON | D32: LENARGE | E32: Mariana Martins | G32: 46029 | H32: 0 | I32: ATENDIDO | J32: PABLO | K32: TORRE | L32: Rastreador da sascar não esta reportando. | M32: TCL9B29 | N32: 46031 | O32: =IF(N32="","SEM DATA APONTADA",(IF(B32="FINALIZADO", "CONCLUÍDO",(IF(B32="ANALISADO", "ANALISADO",IF(N32<TODAY(), "VENCIDO", IF(N32=TODAY(), "VENCE HOJE", IF(N32<=TODAY()+5,"VENCENDO", "NO PRAZO")))))))) -> CONCLUÍDO | P32: Foi diagnosticado que o módulo da sasca estava apresentando falhas. | Q32: 46031
A33: 2026000029 | B33: FINALIZADO | C33: DIEGO | D33: FACSS | E33: Diego Sena | G33: 46029 | H33: 0 | I33: ATENDIDO | J33: MARLON | K33: SUPORTE | L33: Criar usuario para Transportadora Beira Rio | N33: 46029 | O33: =IF(N33="","SEM DATA APONTADA",(IF(B33="FINALIZADO", "CONCLUÍDO",(IF(B33="ANALISADO", "ANALISADO",IF(N33<TODAY(), "VENCIDO", IF(N33=TODAY(), "VENCE HOJE", IF(N33<=TODAY()+5,"VENCENDO", "NO PRAZO")))))))) -> CONCLUÍDO | P33: Usuario criado com sucesso. | Q33: 07/012026
A34: 2026000030 | B34: FINALIZADO | C34: MARLON | D34: LENARGE | E34: Heloiza Carvalho | G34: 45665 | H34: 0 | I34: ATENDIDO | J34: MARLON | K34: SUPORTE | L34: Veículos não estão sendo exibidos no login do vídeo monitoramento FACSS | N34: 45665 | O34: =IF(N34="","SEM DATA APONTADA",(IF(B34="FINALIZADO", "CONCLUÍDO",(IF(B34="ANALISADO", "ANALISADO",IF(N34<TODAY(), "VENCIDO", IF(N34=TODAY(), "VENCE HOJE", IF(N34<=TODAY()+5,"VENCENDO", "NO PRAZO")))))))) -> CONCLUÍDO | P34: Adicionamos as frotas para o usuario do cliente | Q34: 46050
A35: 2026000031 | B35: FINALIZADO | C35: MARLON | D35: LENARGE | E35: Salvador | G35: 45666 | H35: 0 | I35: ATENDIDO | J35: DIEGO | K35: TELEMETRIA | L35: Veiculo não apresenta dados de telemetria | M35: RBE5G92 | N35: 46034 | O35: =IF(N35="","SEM DATA APONTADA",(IF(B35="FINALIZADO", "CONCLUÍDO",(IF(B35="ANALISADO", "ANALISADO",IF(N35<TODAY(), "VENCIDO", IF(N35=TODAY(), "VENCE HOJE", IF(N35<=TODAY()+5,"VENCENDO", "NO PRAZO")))))))) -> CONCLUÍDO | Q35: =N35 -> 46034
A36: 2026000032 | B36: ABERTA | C36: DIEGO | D36: FACSS | E36: Telemetria | G36: 46034 | H36: 0 | I36: MELHORIA/EVOLUÇÃO | J36: NEILOR | K36: P&D | L36: Mercedes Benz não reporta freio motor | N36: 46083 | O36: =IF(N36="","SEM DATA APONTADA",(IF(B36="FINALIZADO", "CONCLUÍDO",(IF(B36="ANALISADO", "ANALISADO",IF(N36<TODAY(), "VENCIDO", IF(N36=TODAY(), "VENCE HOJE", IF(N36<=TODAY()+5,"VENCENDO", "NO PRAZO")))))))) -> VENCIDO
A37: 2026000033 | B37: ABERTA | C37: DIEGO | D37: FACSS | E37: Telemetria | G37: 46034 | H37: 0 | I37: MELHORIA/EVOLUÇÃO | J37: NEILOR | K37: P&D | L37: Scania Super não reporta freio motor | N37: 46083 | O37: =IF(N37="","SEM DATA APONTADA",(IF(B37="FINALIZADO", "CONCLUÍDO",(IF(B37="ANALISADO", "ANALISADO",IF(N37<TODAY(), "VENCIDO", IF(N37=TODAY(), "VENCE HOJE", IF(N37<=TODAY()+5,"VENCENDO", "NO PRAZO")))))))) -> VENCIDO
A38: 2026000034 | B38: ABERTA | C38: DIEGO | D38: FACSS | E38: Telemetria | G38: 46034 | H38: 0 | I38: MELHORIA/EVOLUÇÃO | J38: NEILOR | K38: P&D | L38: Iveco não reporta freio motorFhor | N38: 46083 | O38: =IF(N38="","SEM DATA APONTADA",(IF(B38="FINALIZADO", "CONCLUÍDO",(IF(B38="ANALISADO", "ANALISADO",IF(N38<TODAY(), "VENCIDO", IF(N38=TODAY(), "VENCE HOJE", IF(N38<=TODAY()+5,"VENCENDO", "NO PRAZO")))))))) -> VENCIDO
A39: 2026000035 | B39: FINALIZADO | C39: DIEGO | D39: APERAM Carvão | E39: Telemetria | G39: 45955 | H39: 0 | I39: ATENDIDO | J39: MARLON | K39: SUPORTE | L39: Trocar módulo | M39: RUB4G45 | O39: =IF(N39="","SEM DATA APONTADA",(IF(B39="FINALIZADO", "CONCLUÍDO",(IF(B39="ANALISADO", "ANALISADO",IF(N39<TODAY(), "VENCIDO", IF(N39=TODAY(), "VENCE HOJE", IF(N39<=TODAY()+5,"VENCENDO", "NO PRAZO")))))))) -> SEM DATA APONTADA | P39: Sem solução temporariamente | Q39: 46139
A40: 2026000036 | B40: FINALIZADO | C40: DIEGO | D40: GTS | E40: Telemetria | G40: 45995 | H40: 0 | I40: ATENDIDO | J40: REINALDO | K40: SUPORTE | L40: Trocar módulo | M40: TDA1J81 | N40: 46035 | O40: =IF(N40="","SEM DATA APONTADA",(IF(B40="FINALIZADO", "CONCLUÍDO",(IF(B40="ANALISADO", "ANALISADO",IF(N40<TODAY(), "VENCIDO", IF(N40=TODAY(), "VENCE HOJE", IF(N40<=TODAY()+5,"VENCENDO", "NO PRAZO")))))))) -> CONCLUÍDO | P40: Cliente decidiu não prosseguir com a telemetria FACSS | Q40: 46035
A41: 2026000037 | B41: FINALIZADO | C41: DIEGO | D41: APERAM Carvão | E41: Telemetria | G41: 46014 | H41: 0 | I41: ATENDIDO | J41: MARLON | K41: SUPORTE | L41: Trocar módulo | M41: SJK9G35 | N41: 46051 | O41: =IF(N41="","SEM DATA APONTADA",(IF(B41="FINALIZADO", "CONCLUÍDO",(IF(B41="ANALISADO", "ANALISADO",IF(N41<TODAY(), "VENCIDO", IF(N41=TODAY(), "VENCE HOJE", IF(N41<=TODAY()+5,"VENCENDO", "NO PRAZO")))))))) -> CONCLUÍDO | P41: Veiculo em manitenção após sinistro | Q41: 46051
A42: 2026000038 | B42: FINALIZADO | C42: DIEGO | D42: GTS | E42: Telemetria | G42: 46020 | H42: 0 | I42: ATENDIDO | J42: REINALDO | K42: SUPORTE | L42: Trocar módulo | M42: TDJ3D70 | N42: 46035 | O42: =IF(N42="","SEM DATA APONTADA",(IF(B42="FINALIZADO", "CONCLUÍDO",(IF(B42="ANALISADO", "ANALISADO",IF(N42<TODAY(), "VENCIDO", IF(N42=TODAY(), "VENCE HOJE", IF(N42<=TODAY()+5,"VENCENDO", "NO PRAZO")))))))) -> CONCLUÍDO | P42: Cliente decidiu não prosseguir com a telemetria FACSS | Q42: 46035
A43: 2026000039 | B43: FINALIZADO | C43: DIEGO | D43: P&W | E43: Telemetria | G43: 46020 | H43: 0 | I43: ATENDIDO | J43: MARLON | K43: SUPORTE | L43: Trocar módulo | M43: TCX5C15 | N43: 46049 | O43: =IF(N43="","SEM DATA APONTADA",(IF(B43="FINALIZADO", "CONCLUÍDO",(IF(B43="ANALISADO", "ANALISADO",IF(N43<TODAY(), "VENCIDO", IF(N43=TODAY(), "VENCE HOJE", IF(N43<=TODAY()+5,"VENCENDO", "NO PRAZO")))))))) -> CONCLUÍDO | P43: Veiculo voltou a reportar | Q43: 46049
A44: 2026000040 | B44: FINALIZADO | C44: DIEGO | D44: BEIRA RIO | E44: Telemetria | G44: 46027 | H44: 0 | I44: ATENDIDO | J44: MARLON | K44: SUPORTE | L44: Trocar módulo | M44: RFA0E81 | N44: 46049 | O44: =IF(N44="","SEM DATA APONTADA",(IF(B44="FINALIZADO", "CONCLUÍDO",(IF(B44="ANALISADO", "ANALISADO",IF(N44<TODAY(), "VENCIDO", IF(N44=TODAY(), "VENCE HOJE", IF(N44<=TODAY()+5,"VENCENDO", "NO PRAZO")))))))) -> CONCLUÍDO | P44: Veiculo voltou a reportar | Q44: 46049
A45: 2026000041 | B45: FINALIZADO | C45: DIEGO | D45: EMF LOGÍSTICA | E45: Telemetria | G45: 46027 | H45: 0 | I45: ATENDIDO | J45: MARLON | K45: SUPORTE | L45: Trocar módulo | M45: RND2F57 | N45: 46049 | O45: =IF(N45="","SEM DATA APONTADA",(IF(B45="FINALIZADO", "CONCLUÍDO",(IF(B45="ANALISADO", "ANALISADO",IF(N45<TODAY(), "VENCIDO", IF(N45=TODAY(), "VENCE HOJE", IF(N45<=TODAY()+5,"VENCENDO", "NO PRAZO")))))))) -> CONCLUÍDO | P45: Sem solução temporariamente | Q45: 46049
A46: 2026000042 | B46: FINALIZADO | C46: DIEGO | D46: EMF LOGÍSTICA | E46: Telemetria | G46: 46027 | H46: 0 | I46: ATENDIDO | J46: REINALDO | K46: SUPORTE | L46: Trocar módulo | M46: RUU5F28 | N46: 46049 | O46: =IF(N46="","SEM DATA APONTADA",(IF(B46="FINALIZADO", "CONCLUÍDO",(IF(B46="ANALISADO", "ANALISADO",IF(N46<TODAY(), "VENCIDO", IF(N46=TODAY(), "VENCE HOJE", IF(N46<=TODAY()+5,"VENCENDO", "NO PRAZO")))))))) -> CONCLUÍDO | P46: Veiculo voltou a reportar | Q46: 46049
A47: 2026000043 | B47: FINALIZADO | C47: DIEGO | D47: EMF LOGÍSTICA | E47: Telemetria | G47: 46027 | H47: 0 | I47: ATENDIDO | J47: MARLON | K47: SUPORTE | L47: Trocar módulo | M47: SWJ2H84 | N47: 46049 | O47: =IF(N47="","SEM DATA APONTADA",(IF(B47="FINALIZADO", "CONCLUÍDO",(IF(B47="ANALISADO", "ANALISADO",IF(N47<TODAY(), "VENCIDO", IF(N47=TODAY(), "VENCE HOJE", IF(N47<=TODAY()+5,"VENCENDO", "NO PRAZO")))))))) -> CONCLUÍDO | P47: Sem solução temporariamente | Q47: 46049
A48: 2026000044 | B48: FINALIZADO | C48: DIEGO | D48: TRANSMOREIRA | E48: Telemetria | G48: 46027 | H48: 0 | I48: ATENDIDO | J48: MARLON | K48: SUPORTE | L48: Trocar módulo | M48: TXA2B39 | N48: 46051 | O48: =IF(N48="","SEM DATA APONTADA",(IF(B48="FINALIZADO", "CONCLUÍDO",(IF(B48="ANALISADO", "ANALISADO",IF(N48<TODAY(), "VENCIDO", IF(N48=TODAY(), "VENCE HOJE", IF(N48<=TODAY()+5,"VENCENDO", "NO PRAZO")))))))) -> CONCLUÍDO | P48: Empresa em fase de teste, não vamos mandar o tecnico averiguar a situação. | Q48: 46051
A49: 2026000046 | B49: FINALIZADO | C49: DIEGO | D49: APERAM Carvão | E49: Telemetria | G49: 46028 | H49: 0 | I49: ATENDIDO | J49: MARLON | K49: SUPORTE | L49: Trocar módulo | M49: SJO0F60 | N49: 46049 | O49: =IF(N49="","SEM DATA APONTADA",(IF(B49="FINALIZADO", "CONCLUÍDO",(IF(B49="ANALISADO", "ANALISADO",IF(N49<TODAY(), "VENCIDO", IF(N49=TODAY(), "VENCE HOJE", IF(N49<=TODAY()+5,"VENCENDO", "NO PRAZO")))))))) -> CONCLUÍDO | P49: Veiculo voltou a reportar | Q49: 46049
A50: 2026000047 | B50: FINALIZADO | C50: DIEGO | D50: EMF LOGÍSTICA | E50: Telemetria | G50: 46016 | H50: 0 | I50: ATENDIDO | J50: PABLO | K50: TORRE | L50: Dashboard da EMF não está mostrando o filtro de veículo cadastrado | N50: 46042 | O50: =IF(N50="","SEM DATA APONTADA",(IF(B50="FINALIZADO", "CONCLUÍDO",(IF(B50="ANALISADO", "ANALISADO",IF(N50<TODAY(), "VENCIDO", IF(N50=TODAY(), "VENCE HOJE", IF(N50<=TODAY()+5,"VENCENDO", "NO PRAZO")))))))) -> CONCLUÍDO | Q50: 46042
A51: 2026000048 | B51: FINALIZADO | C51: DIEGO | D51: EMF LOGÍSTICA | E51: Telemetria | G51: 45986 | H51: 0 | I51: ATENDIDO | J51: MARLON | K51: SUPORTE | L51: Divergência com recebimento de iO's | M51: SIB6B68 | N51: 46084 | O51: =IF(N51="","SEM DATA APONTADA",(IF(B51="FINALIZADO", "CONCLUÍDO",(IF(B51="ANALISADO", "ANALISADO",IF(N51<TODAY(), "VENCIDO", IF(N51=TODAY(), "VENCE HOJE", IF(N51<=TODAY()+5,"VENCENDO", "NO PRAZO")))))))) -> CONCLUÍDO | P51: Sem solução temporariamente | Q51: 46083
A52: 2026000049 | B52: FINALIZADO | C52: DIEGO | D52: EMF LOGÍSTICA | E52: Telemetria | G52: 45986 | H52: 0 | I52: ATENDIDO | J52: MARLON | K52: SUPORTE | L52: Divergência com recebimento de iO's | M52: RFC9A54 | N52: 46084 | O52: =IF(N52="","SEM DATA APONTADA",(IF(B52="FINALIZADO", "CONCLUÍDO",(IF(B52="ANALISADO", "ANALISADO",IF(N52<TODAY(), "VENCIDO", IF(N52=TODAY(), "VENCE HOJE", IF(N52<=TODAY()+5,"VENCENDO", "NO PRAZO")))))))) -> CONCLUÍDO | P52: Sem solução temporariamente | Q52: 46084
A53: 2026000050 | B53: FINALIZADO | C53: DIEGO | D53: PORTINARI | E53: Telemetria | G53: 46002 | H53: 0 | I53: ATENDIDO | J53: MARLON | K53: SUPORTE | L53: Trocar módulo | M53: SJI3A97 | N53: 46083 | O53: =IF(N53="","SEM DATA APONTADA",(IF(B53="FINALIZADO", "CONCLUÍDO",(IF(B53="ANALISADO", "ANALISADO",IF(N53<TODAY(), "VENCIDO", IF(N53=TODAY(), "VENCE HOJE", IF(N53<=TODAY()+5,"VENCENDO", "NO PRAZO")))))))) -> CONCLUÍDO | P53: Sem solução temporariamente | Q53: 46084
A54: 2026000051 | B54: ABERTA | C54: DIEGO | D54: EMF LOGÍSTICA | E54: Telemetria | G54: 45986 | H54: 0 | I54: INCIDENTE NORMAL | J54: NEILOR | K54: P&D | L54: Reportando baixo uso do freio motor | M54: OWQ3G00 | N54: 46083 | O54: =IF(N54="","SEM DATA APONTADA",(IF(B54="FINALIZADO", "CONCLUÍDO",(IF(B54="ANALISADO", "ANALISADO",IF(N54<TODAY(), "VENCIDO", IF(N54=TODAY(), "VENCE HOJE", IF(N54<=TODAY()+5,"VENCENDO", "NO PRAZO")))))))) -> VENCIDO
A55: 2026000052 | B55: ABERTA | C55: DIEGO | D55: PORTINARI | E55: Telemetria | G55: 45986 | H55: 0 | I55: MELHORIA/EVOLUÇÃO | J55: NEILOR | K55: P&D | L55: Avaliar consumo total e média (Problema na litragem da mercedes) | M55: QPZ6021 | N55: 46083 | O55: =IF(N55="","SEM DATA APONTADA",(IF(B55="FINALIZADO", "CONCLUÍDO",(IF(B55="ANALISADO", "ANALISADO",IF(N55<TODAY(), "VENCIDO", IF(N55=TODAY(), "VENCE HOJE", IF(N55<=TODAY()+5,"VENCENDO", "NO PRAZO")))))))) -> VENCIDO
A56: 2026000053 | B56: ABERTA | C56: DIEGO | D56: PORTINARI | E56: Telemetria | G56: 45986 | H56: 0 | I56: MELHORIA/EVOLUÇÃO | J56: NEILOR | K56: P&D | L56: Rpm muito alto (Duvida) | M56: KVO6C97 | N56: 46083 | O56: =IF(N56="","SEM DATA APONTADA",(IF(B56="FINALIZADO", "CONCLUÍDO",(IF(B56="ANALISADO", "ANALISADO",IF(N56<TODAY(), "VENCIDO", IF(N56=TODAY(), "VENCE HOJE", IF(N56<=TODAY()+5,"VENCENDO", "NO PRAZO")))))))) -> VENCIDO
A57: 2026000054 | B57: ABERTA | C57: DIEGO | D57: PORTINARI | E57: Telemetria | G57: 45986 | H57: 0 | I57: MELHORIA/EVOLUÇÃO | J57: NEILOR | K57: P&D | L57: Rpm muito alto (Duvida) | M57: OWJ0772 | N57: 46083 | O57: =IF(N57="","SEM DATA APONTADA",(IF(B57="FINALIZADO", "CONCLUÍDO",(IF(B57="ANALISADO", "ANALISADO",IF(N57<TODAY(), "VENCIDO", IF(N57=TODAY(), "VENCE HOJE", IF(N57<=TODAY()+5,"VENCENDO", "NO PRAZO")))))))) -> VENCIDO
A58: 2026000055 | B58: FINALIZADO | C58: DIEGO | D58: APERAM Carvão | E58: Sidney Alves | G58: 45993 | H58: 0 | I58: ATENDIDO | J58: DIEGO | K58: TELEMETRIA | L58: Km da viagem do dia 30/11/25 não bate com o Dashboard | M58: RUQ5133 | N58: 46059 | O58: =IF(N58="","SEM DATA APONTADA",(IF(B58="FINALIZADO", "CONCLUÍDO",(IF(B58="ANALISADO", "ANALISADO",IF(N58<TODAY(), "VENCIDO", IF(N58=TODAY(), "VENCE HOJE", IF(N58<=TODAY()+5,"VENCENDO", "NO PRAZO")))))))) -> CONCLUÍDO | P58: Houve uma atuação dos desenvolvedores para solucionar todos os problemas iguais a esse no cliente | Q58: 46049
A59: 2026000056 | B59: ABERTA | C59: DIEGO | D59: LENARGE | E59: Telemetria | G59: 46016 | H59: 0 | I59: INCIDENTE NORMAL | J59: NEILOR | K59: P&D | L59: Não está reportando freio motor | M59: SRF0D12 | N59: 46083 | O59: =IF(N59="","SEM DATA APONTADA",(IF(B59="FINALIZADO", "CONCLUÍDO",(IF(B59="ANALISADO", "ANALISADO",IF(N59<TODAY(), "VENCIDO", IF(N59=TODAY(), "VENCE HOJE", IF(N59<=TODAY()+5,"VENCENDO", "NO PRAZO")))))))) -> VENCIDO
A60: 2026000057 | B60: ABERTA | C60: DIEGO | D60: LENARGE | E60: Telemetria | G60: 46016 | H60: 0 | I60: INCIDENTE NORMAL | J60: NEILOR | K60: P&D | L60: Não está reportando freio motor | M60: SIN3G19 | N60: 46083 | O60: =IF(N60="","SEM DATA APONTADA",(IF(B60="FINALIZADO", "CONCLUÍDO",(IF(B60="ANALISADO", "ANALISADO",IF(N60<TODAY(), "VENCIDO", IF(N60=TODAY(), "VENCE HOJE", IF(N60<=TODAY()+5,"VENCENDO", "NO PRAZO")))))))) -> VENCIDO
A61: 2026000058 | B61: FINALIZADO | C61: DIEGO | D61: RLR | E61: Telemetria | G61: 46016 | H61: 0 | I61: ATENDIDO | J61: GABRIEL | K61: TELEMETRIA | L61: Inércia muito alta | M61: RFC4C30 | N61: 46059 | O61: =IF(N61="","SEM DATA APONTADA",(IF(B61="FINALIZADO", "CONCLUÍDO",(IF(B61="ANALISADO", "ANALISADO",IF(N61<TODAY(), "VENCIDO", IF(N61=TODAY(), "VENCE HOJE", IF(N61<=TODAY()+5,"VENCENDO", "NO PRAZO")))))))) -> CONCLUÍDO | P61: Veiculo foi desvinculado | Q61: 46084
A62: 2026000059 | B62: FINALIZADO | C62: DIEGO | D62: LENARGE | E62: Telemetria | G62: 46002 | H62: 0 | I62: ATENDIDO | J62: GABRIEL | K62: TELEMETRIA | L62: Não está reportando inércia | M62: RBG8H66 | N62: 46059 | O62: =IF(N62="","SEM DATA APONTADA",(IF(B62="FINALIZADO", "CONCLUÍDO",(IF(B62="ANALISADO", "ANALISADO",IF(N62<TODAY(), "VENCIDO", IF(N62=TODAY(), "VENCE HOJE", IF(N62<=TODAY()+5,"VENCENDO", "NO PRAZO")))))))) -> CONCLUÍDO | P62: A inicia desse veiculo foi resolvida, mas para a resolução ser definitiva é necessario passar essa alterção para o Torre de contole (A alteração feita foi retirar uma das validações que é feita para verificar se o veiculo esta em inecia, retiramos a validação do delta do speed maior que 0) | Q62: 46059
A63: 2026000060 | B63: ABERTA | C63: DIEGO | D63: LENARGE | E63: Telemetria | G63: 46002 | H63: 0 | I63: INCIDENTE NORMAL | J63: NEILOR | K63: P&D | L63: Não está reportando freio motor | M63: SIN3G19 | N63: 46083 | O63: =IF(N63="","SEM DATA APONTADA",(IF(B63="FINALIZADO", "CONCLUÍDO",(IF(B63="ANALISADO", "ANALISADO",IF(N63<TODAY(), "VENCIDO", IF(N63=TODAY(), "VENCE HOJE", IF(N63<=TODAY()+5,"VENCENDO", "NO PRAZO")))))))) -> VENCIDO
A64: 2026000061 | B64: ABERTA | C64: DIEGO | D64: LENARGE | E64: Telemetria | G64: 46002 | H64: 0 | I64: INCIDENTE NORMAL | J64: NEILOR | K64: P&D | L64: Não está reportando freio motor | M64: ENG5C15 | N64: 46083 | O64: =IF(N64="","SEM DATA APONTADA",(IF(B64="FINALIZADO", "CONCLUÍDO",(IF(B64="ANALISADO", "ANALISADO",IF(N64<TODAY(), "VENCIDO", IF(N64=TODAY(), "VENCE HOJE", IF(N64<=TODAY()+5,"VENCENDO", "NO PRAZO")))))))) -> VENCIDO
A65: 2026000062 | B65: ABERTA | C65: DIEGO | D65: LENARGE | E65: Telemetria | G65: 46002 | H65: 0 | I65: INCIDENTE NORMAL | J65: NEILOR | K65: P&D | L65: Não está reportando freio motor | M65: RJD6F22 | N65: 46083 | O65: =IF(N65="","SEM DATA APONTADA",(IF(B65="FINALIZADO", "CONCLUÍDO",(IF(B65="ANALISADO", "ANALISADO",IF(N65<TODAY(), "VENCIDO", IF(N65=TODAY(), "VENCE HOJE", IF(N65<=TODAY()+5,"VENCENDO", "NO PRAZO")))))))) -> VENCIDO
A66: 2026000063 | B66: ABERTA | C66: DIEGO | D66: LENARGE | E66: Telemetria | G66: 46002 | H66: 0 | I66: INCIDENTE NORMAL | J66: NEILOR | K66: P&D | L66: Não está reportando freio motor | M66: SRF0D12 | N66: 46083 | O66: =IF(N66="","SEM DATA APONTADA",(IF(B66="FINALIZADO", "CONCLUÍDO",(IF(B66="ANALISADO", "ANALISADO",IF(N66<TODAY(), "VENCIDO", IF(N66=TODAY(), "VENCE HOJE", IF(N66<=TODAY()+5,"VENCENDO", "NO PRAZO")))))))) -> VENCIDO
A67: 2026000064 | B67: FINALIZADO | C67: DIEGO | D67: RLR | E67: Cliente | G67: 46003 | H67: 0 | I67: ATENDIDO | J67: GABRIEL | K67: TELEMETRIA | L67: Média muito alta | M67: RFC4C30 | N67: 46059 | O67: =IF(N67="","SEM DATA APONTADA",(IF(B67="FINALIZADO", "CONCLUÍDO",(IF(B67="ANALISADO", "ANALISADO",IF(N67<TODAY(), "VENCIDO", IF(N67=TODAY(), "VENCE HOJE", IF(N67<=TODAY()+5,"VENCENDO", "NO PRAZO")))))))) -> CONCLUÍDO | P67: Veiculo foi desvinculado | Q67: 46084
A68: 2026000065 | B68: ABERTA | C68: DIEGO | D68: P&W | E68: Telemetria | G68: 46006 | H68: 0 | I68: INCIDENTE NORMAL | J68: NEILOR | K68: P&D | L68: Não está reportando freio motor | M68: RNG8H84 | N68: 46083 | O68: =IF(N68="","SEM DATA APONTADA",(IF(B68="FINALIZADO", "CONCLUÍDO",(IF(B68="ANALISADO", "ANALISADO",IF(N68<TODAY(), "VENCIDO", IF(N68=TODAY(), "VENCE HOJE", IF(N68<=TODAY()+5,"VENCENDO", "NO PRAZO")))))))) -> VENCIDO
A69: 2026000066 | B69: ABERTA | C69: DIEGO | D69: LENARGE | E69: Telemetria | G69: 46007 | H69: 0 | I69: INCIDENTE NORMAL | J69: NEILOR | K69: P&D | L69: Não está reportando freio motor | M69: RJH5G17 | N69: 46083 | O69: =IF(N69="","SEM DATA APONTADA",(IF(B69="FINALIZADO", "CONCLUÍDO",(IF(B69="ANALISADO", "ANALISADO",IF(N69<TODAY(), "VENCIDO", IF(N69=TODAY(), "VENCE HOJE", IF(N69<=TODAY()+5,"VENCENDO", "NO PRAZO")))))))) -> VENCIDO
A70: 2026000067 | B70: ABERTA | C70: DIEGO | D70: FASI | E70: Telemetria | G70: 46007 | H70: 0 | I70: INCIDENTE NORMAL | J70: NEILOR | K70: P&D | L70: Média muito alta | M70: RNT6F54 | N70: 46083 | O70: =IF(N70="","SEM DATA APONTADA",(IF(B70="FINALIZADO", "CONCLUÍDO",(IF(B70="ANALISADO", "ANALISADO",IF(N70<TODAY(), "VENCIDO", IF(N70=TODAY(), "VENCE HOJE", IF(N70<=TODAY()+5,"VENCENDO", "NO PRAZO")))))))) -> VENCIDO
A71: 2026000068 | B71: ABERTA | C71: DIEGO | D71: FACSS | E71: Salvador | G71: 46007 | H71: 0 | I71: MELHORIA/EVOLUÇÃO | J71: NEILOR | K71: P&D | L71: Criar novo parâmetro para freio motor na Lenarge | M71: - | N71: 46083 | O71: =IF(N71="","SEM DATA APONTADA",(IF(B71="FINALIZADO", "CONCLUÍDO",(IF(B71="ANALISADO", "ANALISADO",IF(N71<TODAY(), "VENCIDO", IF(N71=TODAY(), "VENCE HOJE", IF(N71<=TODAY()+5,"VENCENDO", "NO PRAZO")))))))) -> VENCIDO
A72: 2026000069 | B72: ABERTA | C72: DIEGO | D72: LENARGE | E72: Cliente | G72: 46010 | H72: 0 | I72: MELHORIA/EVOLUÇÃO | J72: NEILOR | K72: P&D | L72: Analisar a % que o freio motor atuou acima de 1.800 rpm | M72: TTF4A67 | N72: 46083 | O72: =IF(N72="","SEM DATA APONTADA",(IF(B72="FINALIZADO", "CONCLUÍDO",(IF(B72="ANALISADO", "ANALISADO",IF(N72<TODAY(), "VENCIDO", IF(N72=TODAY(), "VENCE HOJE", IF(N72<=TODAY()+5,"VENCENDO", "NO PRAZO")))))))) -> VENCIDO
A73: 2026000070 | B73: FINALIZADO | C73: DIEGO | D73: TRANSKOMPA | E73: Cliente | G73: 46020 | H73: 0 | I73: ATENDIDO | J73: GABRIEL | K73: TELEMETRIA | L73: Inércia muito baixa | M73: FWF6A05 | N73: 46059 | O73: =IF(N73="","SEM DATA APONTADA",(IF(B73="FINALIZADO", "CONCLUÍDO",(IF(B73="ANALISADO", "ANALISADO",IF(N73<TODAY(), "VENCIDO", IF(N73=TODAY(), "VENCE HOJE", IF(N73<=TODAY()+5,"VENCENDO", "NO PRAZO")))))))) -> CONCLUÍDO | P73: A inicia desse veiculo foi resolvida, mas para a resolução ser definitiva é necessario passar essa alterção para o Torre de contole (A alteração feita foi retirar uma das validações que é feita para verificar se o veiculo esta em inecia, retiramos a validação do delta do speed maior que 0) | Q73: 46059
A74: 2026000071 | B74: FINALIZADO | C74: DIEGO | D74: PORTINARI | E74: Telemetria | G74: 46024 | H74: 0 | I74: ATENDIDO | J74: MARLON | K74: SUPORTE | L74: Divergência com recebimento de iO's | M74: QNV4C44 | N74: 46084 | O74: =IF(N74="","SEM DATA APONTADA",(IF(B74="FINALIZADO", "CONCLUÍDO",(IF(B74="ANALISADO", "ANALISADO",IF(N74<TODAY(), "VENCIDO", IF(N74=TODAY(), "VENCE HOJE", IF(N74<=TODAY()+5,"VENCENDO", "NO PRAZO")))))))) -> CONCLUÍDO | P74: Foi reenviada a config | Q74: 46084
A75: 2026000072 | B75: FINALIZADO | C75: DIEGO | D75: LENARGE | E75: Cliente | G75: 46028 | H75: 0 | I75: ATENDIDO | J75: GABRIEL | K75: TELEMETRIA | L75: Não está reportando dados | M75: RKR7J21 | N75: 46059 | O75: =IF(N75="","SEM DATA APONTADA",(IF(B75="FINALIZADO", "CONCLUÍDO",(IF(B75="ANALISADO", "ANALISADO",IF(N75<TODAY(), "VENCIDO", IF(N75=TODAY(), "VENCE HOJE", IF(N75<=TODAY()+5,"VENCENDO", "NO PRAZO")))))))) -> CONCLUÍDO | P75: Voltou a reportar no Dashboard. | Q75: 46034
A76: 2026000073 | B76: FINALIZADO | C76: DIEGO | D76: LENARGE | E76: Cliente | G76: 46029 | H76: 0 | I76: ATENDIDO | J76: GABRIEL | K76: TELEMETRIA | L76: Não está gerando performance | M76: TTR8H42 | N76: 46059 | O76: =IF(N76="","SEM DATA APONTADA",(IF(B76="FINALIZADO", "CONCLUÍDO",(IF(B76="ANALISADO", "ANALISADO",IF(N76<TODAY(), "VENCIDO", IF(N76=TODAY(), "VENCE HOJE", IF(N76<=TODAY()+5,"VENCENDO", "NO PRAZO")))))))) -> CONCLUÍDO | P76: Voltou a reportar no Dashboard. | Q76: 46034
A77: 2026000074 | B77: FINALIZADO | C77: MARLON | D77: EMF LOGÍSTICA | E77: Rafael Paraense | G77: 46034 | H77: 0 | I77: ATENDIDO | J77: PEDRO | K77: SUPORTE | L77: Módulos novos pra veiculos | M77: UHN9C67 | N77: 46036 | O77: =IF(N77="","SEM DATA APONTADA",(IF(B77="FINALIZADO", "CONCLUÍDO",(IF(B77="ANALISADO", "ANALISADO",IF(N77<TODAY(), "VENCIDO", IF(N77=TODAY(), "VENCE HOJE", IF(N77<=TODAY()+5,"VENCENDO", "NO PRAZO")))))))) -> CONCLUÍDO | P77: Preparação de módulos e envio para o João Pedro | Q77: 46036
B78: FINALIZADO | D78: EMF LOGÍSTICA | H78: 0 | I78: ATENDIDO | J78: PEDRO | K78: SUPORTE | L78: Módulos novos pra veiculos | M78: UHN9D07 | N78: 46036 | O78: =IF(N78="","SEM DATA APONTADA",(IF(B78="FINALIZADO", "CONCLUÍDO",(IF(B78="ANALISADO", "ANALISADO",IF(N78<TODAY(), "VENCIDO", IF(N78=TODAY(), "VENCE HOJE", IF(N78<=TODAY()+5,"VENCENDO", "NO PRAZO")))))))) -> CONCLUÍDO | P78: Preparação de módulos e envio para o João Pedro | Q78: 46036
B79: FINALIZADO | D79: EMF LOGÍSTICA | H79: 0 | I79: ATENDIDO | J79: PEDRO | K79: SUPORTE | L79: Módulos novos pra veiculos | M79: UHN9G67 | N79: 46036 | O79: =IF(N79="","SEM DATA APONTADA",(IF(B79="FINALIZADO", "CONCLUÍDO",(IF(B79="ANALISADO", "ANALISADO",IF(N79<TODAY(), "VENCIDO", IF(N79=TODAY(), "VENCE HOJE", IF(N79<=TODAY()+5,"VENCENDO", "NO PRAZO")))))))) -> CONCLUÍDO | P79: Preparação de módulos e envio para o João Pedro | Q79: 46036
B80: FINALIZADO | D80: EMF LOGÍSTICA | H80: 0 | I80: ATENDIDO | J80: PEDRO | K80: SUPORTE | L80: Módulos novos pra veiculos | M80: UHN9D17 | N80: 46036 | O80: =IF(N80="","SEM DATA APONTADA",(IF(B80="FINALIZADO", "CONCLUÍDO",(IF(B80="ANALISADO", "ANALISADO",IF(N80<TODAY(), "VENCIDO", IF(N80=TODAY(), "VENCE HOJE", IF(N80<=TODAY()+5,"VENCENDO", "NO PRAZO")))))))) -> CONCLUÍDO | P80: Preparação de módulos e envio para o João Pedro | Q80: 46036
B81: FINALIZADO | D81: EMF LOGÍSTICA | H81: 0 | I81: ATENDIDO | J81: PEDRO | K81: SUPORTE | L81: Módulos novos pra veiculos | M81: UHN9D27 | N81: 46036 | O81: =IF(N81="","SEM DATA APONTADA",(IF(B81="FINALIZADO", "CONCLUÍDO",(IF(B81="ANALISADO", "ANALISADO",IF(N81<TODAY(), "VENCIDO", IF(N81=TODAY(), "VENCE HOJE", IF(N81<=TODAY()+5,"VENCENDO", "NO PRAZO")))))))) -> CONCLUÍDO | P81: Preparação de módulos e envio para o João Pedro | Q81: 46036
B82: FINALIZADO | D82: EMF LOGÍSTICA | H82: 0 | I82: ATENDIDO | J82: PEDRO | K82: SUPORTE | L82: Módulos novos pra veiculos | M82: UHN9G97 | N82: 46036 | O82: =IF(N82="","SEM DATA APONTADA",(IF(B82="FINALIZADO", "CONCLUÍDO",(IF(B82="ANALISADO", "ANALISADO",IF(N82<TODAY(), "VENCIDO", IF(N82=TODAY(), "VENCE HOJE", IF(N82<=TODAY()+5,"VENCENDO", "NO PRAZO")))))))) -> CONCLUÍDO | P82: Preparação de módulos e envio para o João Pedro | Q82: 46036
B83: FINALIZADO | D83: EMF LOGÍSTICA | H83: 0 | I83: ATENDIDO | J83: PEDRO | K83: SUPORTE | L83: Módulos novos pra veiculos | M83: UHN9E07 | N83: 46036 | O83: =IF(N83="","SEM DATA APONTADA",(IF(B83="FINALIZADO", "CONCLUÍDO",(IF(B83="ANALISADO", "ANALISADO",IF(N83<TODAY(), "VENCIDO", IF(N83=TODAY(), "VENCE HOJE", IF(N83<=TODAY()+5,"VENCENDO", "NO PRAZO")))))))) -> CONCLUÍDO | P83: Preparação de módulos e envio para o João Pedro | Q83: 46059
A84: 2026000075 | B84: FINALIZADO | C84: DIEGO | D84: LENARGE | E84: Cliente | G84: 46029 | H84: 0 | I84: ATENDIDO | J84: GABRIEL | K84: TELEMETRIA | L84: Veículo está reportando inércia de forma incorreta | M84: SRM3D70 | N84: 46059 | O84: =IF(N84="","SEM DATA APONTADA",(IF(B84="FINALIZADO", "CONCLUÍDO",(IF(B84="ANALISADO", "ANALISADO",IF(N84<TODAY(), "VENCIDO", IF(N84=TODAY(), "VENCE HOJE", IF(N84<=TODAY()+5,"VENCENDO", "NO PRAZO")))))))) -> CONCLUÍDO | P84: Caso segue em análise na OS 2026000027 | Q84: 46049
A85: 2026000076 | B85: FINALIZADO | C85: DIEGO | D85: APERAM Carvão | E85: Telemetria | G85: 46031 | H85: 0 | I85: ATENDIDO | J85: DIEGO | K85: TELEMETRIA | L85: Desenvolver estudo sobre trecho vs Dashboard | N85: 46038 | O85: =IF(N85="","SEM DATA APONTADA",(IF(B85="FINALIZADO", "CONCLUÍDO",(IF(B85="ANALISADO", "ANALISADO",IF(N85<TODAY(), "VENCIDO", IF(N85=TODAY(), "VENCE HOJE", IF(N85<=TODAY()+5,"VENCENDO", "NO PRAZO")))))))) -> CONCLUÍDO | P85: Estudo de caso realizado e levado para pós análise junto ao P&D. | Q85: 46036
A86: 2026000077 | B86: FINALIZADO | C86: DIEGO | D86: APERAM Carvão | E86: Telemetria | G86: 46031 | H86: 0 | I86: ATENDIDO | J86: DIEGO | K86: TELEMETRIA | L86: Desenvolver resposta para o cliente | N86: 46038 | O86: =IF(N86="","SEM DATA APONTADA",(IF(B86="FINALIZADO", "CONCLUÍDO",(IF(B86="ANALISADO", "ANALISADO",IF(N86<TODAY(), "VENCIDO", IF(N86=TODAY(), "VENCE HOJE", IF(N86<=TODAY()+5,"VENCENDO", "NO PRAZO")))))))) -> CONCLUÍDO | P86: Respondido pelo CS, "conforme combinado a análise já foi concluída e confirmamos que a situação será solucionada até sexta-feira dia 23." | Q86: 46038
A87: 2026000078 | B87: FINALIZADO | C87: MARLON | D87: APERAM Carvão | E87: João Paulo | G87: 46031 | H87: 0 | I87: ATENDIDO | J87: MARLON | K87: SUPORTE | L87: Liberar acesso ao Tracking para o cliente | N87: 46038 | O87: =IF(N87="","SEM DATA APONTADA",(IF(B87="FINALIZADO", "CONCLUÍDO",(IF(B87="ANALISADO", "ANALISADO",IF(N87<TODAY(), "VENCIDO", IF(N87=TODAY(), "VENCE HOJE", IF(N87<=TODAY()+5,"VENCENDO", "NO PRAZO")))))))) -> CONCLUÍDO | P87: Acesso liberado | Q87: 46038
A88: 2026000079 | B88: FINALIZADO | C88: MARLON | D88: APERAM Carvão | E88: João Paulo | G88: 46031 | H88: 0 | I88: ATENDIDO | J88: NEILOR | K88: P&D | L88: Formalizar por email o estudo de caso sobre a litragem do Mercedes Benz | N88: 46081 | O88: =IF(N88="","SEM DATA APONTADA",(IF(B88="FINALIZADO", "CONCLUÍDO",(IF(B88="ANALISADO", "ANALISADO",IF(N88<TODAY(), "VENCIDO", IF(N88=TODAY(), "VENCE HOJE", IF(N88<=TODAY()+5,"VENCENDO", "NO PRAZO")))))))) -> CONCLUÍDO | P88: Email enviado ao cliente no dia 15/jan e o cliente já interagiu e compreendeu | Q88: 46037
A89: 2026000080 | B89: FINALIZADO | C89: DIEGO | D89: LENARGE | E89: Leandro Galdono | G89: 46035 | H89: 0 | I89: ATENDIDO | J89: DIEGO | K89: TELEMETRIA | L89: Não está reportando telemetria | M89: SQV1D61 | N89: 46038 | O89: =IF(N89="","SEM DATA APONTADA",(IF(B89="FINALIZADO", "CONCLUÍDO",(IF(B89="ANALISADO", "ANALISADO",IF(N89<TODAY(), "VENCIDO", IF(N89=TODAY(), "VENCE HOJE", IF(N89<=TODAY()+5,"VENCENDO", "NO PRAZO")))))))) -> CONCLUÍDO | P89: Será realizado a substituuição do módulo, pois estava há 4 meses sem reportar | Q89: 46035
A90: 2026000081 | B90: FINALIZADO | C90: DIEGO | D90: LENARGE | E90: Cliente | G90: 46035 | H90: 0 | I90: ATENDIDO | J90: GABRIEL | K90: TELEMETRIA | L90: Não está reportando telemetria | M90: TTR8H42 | N90: 46038 | O90: =IF(N90="","SEM DATA APONTADA",(IF(B90="FINALIZADO", "CONCLUÍDO",(IF(B90="ANALISADO", "ANALISADO",IF(N90<TODAY(), "VENCIDO", IF(N90=TODAY(), "VENCE HOJE", IF(N90<=TODAY()+5,"VENCENDO", "NO PRAZO")))))))) -> CONCLUÍDO | P90: Veículo reportando no Traccar e no Dashboard. | Q90: 46036
A91: 2026000082 | B91: FINALIZADO | C91: DIEGO | D91: LENARGE | E91: Cliente | G91: 46035 | H91: 0 | I91: ATENDIDO | J91: GABRIEL | K91: TELEMETRIA | L91: Não está reportando telemetria | M91: TTQ9A79 | N91: 46038 | O91: =IF(N91="","SEM DATA APONTADA",(IF(B91="FINALIZADO", "CONCLUÍDO",(IF(B91="ANALISADO", "ANALISADO",IF(N91<TODAY(), "VENCIDO", IF(N91=TODAY(), "VENCE HOJE", IF(N91<=TODAY()+5,"VENCENDO", "NO PRAZO")))))))) -> CONCLUÍDO | P91: Veículo reportando no Traccar e no Dashboard. | Q91: 46036
A92: 2026000083 | B92: FINALIZADO | C92: MARLON | D92: LENARGE | E92: Salvador | G92: 46035 | H92: 0 | I92: ATENDIDO | J92: DIEGO | K92: TELEMETRIA | L92: Não está reportando telemetria | M92: RBE5G92 | N92: 46038 | O92: =IF(N92="","SEM DATA APONTADA",(IF(B92="FINALIZADO", "CONCLUÍDO",(IF(B92="ANALISADO", "ANALISADO",IF(N92<TODAY(), "VENCIDO", IF(N92=TODAY(), "VENCE HOJE", IF(N92<=TODAY()+5,"VENCENDO", "NO PRAZO")))))))) -> CONCLUÍDO | P92: Foi enviado a config e o módul voltou a reportar | Q92: 46035
A93: 2026000084 | B93: FINALIZADO | C93: DIEGO | D93: FACSS | E93: Telemetria | G93: 46035 | H93: 0 | I93: ATENDIDO | J93: PABLO | K93: TORRE | L93: Melhoria: colocar o contador no ranking de veiculos/motoristas em todas as frotas (como na APERAM Carvão) | N93: 46059 | O93: =IF(N93="","SEM DATA APONTADA",(IF(B93="FINALIZADO", "CONCLUÍDO",(IF(B93="ANALISADO", "ANALISADO",IF(N93<TODAY(), "VENCIDO", IF(N93=TODAY(), "VENCE HOJE", IF(N93<=TODAY()+5,"VENCENDO", "NO PRAZO")))))))) -> CONCLUÍDO | Q93: 46057
A94: 2026000085 | B94: FINALIZADO | C94: MARLON | D94: LENARGE | E94: Letícia Cristina | G94: 46035 | H94: 0 | I94: ATENDIDO | J94: MARLON | K94: SUPORTE | L94: Falha freios / Falha elétrica / Perda de funcionalidade / Tacógrafo com defeito / Funcionalidade transmissão reduzida. | M94: RBE9D16 | N94: 46035 | O94: =IF(N94="","SEM DATA APONTADA",(IF(B94="FINALIZADO", "CONCLUÍDO",(IF(B94="ANALISADO", "ANALISADO",IF(N94<TODAY(), "VENCIDO", IF(N94=TODAY(), "VENCE HOJE", IF(N94<=TODAY()+5,"VENCENDO", "NO PRAZO")))))))) -> CONCLUÍDO | P94: Enviei a config | Q94: 46035
A95: 2026000086 | B95: FINALIZADO | C95: MARLON | D95: LENARGE | E95: Mariana Martins | G95: 46035 | H95: 0 | I95: ATENDIDO | J95: MARLON | K95: SUPORTE | L95: Criar usuario para funcionário do controle de manutenção e espelhar acesso. | N95: 46035 | O95: =IF(N95="","SEM DATA APONTADA",(IF(B95="FINALIZADO", "CONCLUÍDO",(IF(B95="ANALISADO", "ANALISADO",IF(N95<TODAY(), "VENCIDO", IF(N95=TODAY(), "VENCE HOJE", IF(N95<=TODAY()+5,"VENCENDO", "NO PRAZO")))))))) -> CONCLUÍDO | P95: Criei o usuario e espelhei o acesso. | Q95: 46035
A96: 2026000087 | B96: FINALIZADO | C96: DIEGO | D96: GTS | E96: Telemetria | G96: 46035 | H96: 0 | I96: ATENDIDO | J96: REINALDO | K96: SUPORTE | L96: Retirar módulos de teste | M96: TDA1J81 | O96: =IF(N96="","SEM DATA APONTADA",(IF(B96="FINALIZADO", "CONCLUÍDO",(IF(B96="ANALISADO", "ANALISADO",IF(N96<TODAY(), "VENCIDO", IF(N96=TODAY(), "VENCE HOJE", IF(N96<=TODAY()+5,"VENCENDO", "NO PRAZO")))))))) -> SEM DATA APONTADA | P96: Cliente ainda não definiu a retirada dos módulos | Q96: 46048
A97: 2026000088 | B97: FINALIZADO | C97: DIEGO | D97: GTS | E97: Telemetria | G97: 46035 | H97: 0 | I97: ATENDIDO | J97: REINALDO | K97: SUPORTE | L97: Retirar módulos de teste | M97: TDJ3D70 | O97: =IF(N97="","SEM DATA APONTADA",(IF(B97="FINALIZADO", "CONCLUÍDO",(IF(B97="ANALISADO", "ANALISADO",IF(N97<TODAY(), "VENCIDO", IF(N97=TODAY(), "VENCE HOJE", IF(N97<=TODAY()+5,"VENCENDO", "NO PRAZO")))))))) -> SEM DATA APONTADA | P97: Cliente ainda não definiu a retirada dos módulos | Q97: 46048
A98: 2026000089 | B98: FINALIZADO | C98: DIEGO | D98: GTS | E98: Telemetria | G98: 46035 | H98: 0 | I98: ATENDIDO | J98: REINALDO | K98: SUPORTE | L98: Retirar módulos de teste | M98: TXT6J11 | O98: =IF(N98="","SEM DATA APONTADA",(IF(B98="FINALIZADO", "CONCLUÍDO",(IF(B98="ANALISADO", "ANALISADO",IF(N98<TODAY(), "VENCIDO", IF(N98=TODAY(), "VENCE HOJE", IF(N98<=TODAY()+5,"VENCENDO", "NO PRAZO")))))))) -> SEM DATA APONTADA | P98: Cliente ainda não definiu a retirada dos módulos | Q98: 46048
A99: 2026000090 | B99: FINALIZADO | C99: DIEGO | D99: GTS | E99: Telemetria | G99: 46035 | H99: 0 | I99: ATENDIDO | J99: REINALDO | K99: SUPORTE | L99: Retirar módulos de teste | M99: TXT6J33 | O99: =IF(N99="","SEM DATA APONTADA",(IF(B99="FINALIZADO", "CONCLUÍDO",(IF(B99="ANALISADO", "ANALISADO",IF(N99<TODAY(), "VENCIDO", IF(N99=TODAY(), "VENCE HOJE", IF(N99<=TODAY()+5,"VENCENDO", "NO PRAZO")))))))) -> SEM DATA APONTADA | P99: Cliente ainda não definiu a retirada dos módulos | Q99: 46048
A100: 2026000091 | B100: FINALIZADO | C100: DIEGO | D100: GTS | E100: Telemetria | G100: 46035 | H100: 0 | I100: ATENDIDO | J100: REINALDO | K100: SUPORTE | L100: Retirar módulos de teste | M100: TXT7B52 | O100: =IF(N100="","SEM DATA APONTADA",(IF(B100="FINALIZADO", "CONCLUÍDO",(IF(B100="ANALISADO", "ANALISADO",IF(N100<TODAY(), "VENCIDO", IF(N100=TODAY(), "VENCE HOJE", IF(N100<=TODAY()+5,"VENCENDO", "NO PRAZO")))))))) -> SEM DATA APONTADA | P100: Cliente ainda não definiu a retirada dos módulos | Q100: 46048
...

Sheet Módulos
A1: PLACA | B1: Marca | C1: Modelo | D1: Ano Modelo | E1: ID Módulo Atual | F1: Chip | G1: EMPRESA | H1: Data Instalação | I1: Situação | J1: Observação | K1: Cadastrado no APP | L1: FALHA ENCONTRADA | M1: ULTIMO REPORT
A2: LNR TTP6B56 3769 | B2: VOLVO | C2: FH 500 6X2T | D2: 2026 | E2: 860369054733769 | F2: ESEYE | G2: LENARGE | H2: 42348 | I2: ATIVO | M2: modulo cadastrado traccar
A3: LNR TTR5E46 5285 | B3: VOLVO | C3: FH 500 6X2T | D3: 2026 | E3: 860369054405285 | F3: ESEYE | G3: LENARGE | H3: 42348 | I3: ATIVO | M3: modulo cadastrado traccar
A4: LNR RKP6D22 1425 | B4: VOLVO | C4: FH 460 6X2 | D4: 2022 | E4: 860369054161425 | F4: ESEYE | G4: LENARGE | H4: 45658 | I4: ATIVO
A5: LNR RKP6D21 9759 | B5: VOLVO | C5: FH 460 6X2 | D5: 2022 | E5: 860369054159759 | F5: ESEYE | G5: LENARGE | H5: 45658 | I5: ATIVO
A6: RLR QPT0I86 6403 | B6: SCANIA | C6: FH 460 6X2T | D6: 2019 | E6: 860369052136403 | F6: ESEYE | G6: RLR | H6: 45809 | I6: ATIVO | N6: conferencia 24/04
A7: RLR QQO4500 7709 | B7: SCANIA | C7: FH 460 6X2T | E7: 860369052467709 | F7: ESEYE | G7: RLR | H7: 45809 | I7: ATIVO | N7: conferencia 24/04
A8: RLR RFC1I73 7024 | B8: DAF | C8: XF105 FTS 460A 2020 | E8: 860369054187024 | F8: ESEYE | G8: RLR | H8: 45809 | I8: ATIVO | N8: conferencia 24/04
A9: RLR RFC4C29 0679 | B9: VOLVO | C9: FH 460 6X2T 2021 | D9: 2021 | E9: 860369051060679 | F9: ARQIA | G9: RLR | H9: 45809 | I9: ATIVO
A10: RLR RMF3I15 7369 | B10: VOLVO | C10: FH 500 6X2T 2021 | D10: 2021 | E10: 860369051067369 | F10: ARQIA | G10: RLR | H10: 45809 | I10: ATIVO
A11: RLR RMW4I63 8562 | B11: SCANIA | C11: R450 A6X2 2021 | E11: 860369052168562 | F11: ARQIA | G11: RLR | H11: 45809 | I11: ATIVO | N11: conferencia 24/04
A12: RLR RMW4I74 6744 | B12: SCANIA | C12: R450 A6X2 2021 | E12: 860369052116744 | F12: ARQIA | G12: RLR | H12: 45809 | I12: ATIVO | N12: conferencia 24/04
A13: RLR RMW9G19 7192 | B13: SCANIA | C13: R450 A6X2 2021 | E13: 860369052167192 | F13: ARQIA | G13: RLR | H13: 45809 | I13: ATIVO | N13: conferencia 24/04
A14: RLR RMY5C47 4086 | B14: SCANIA | C14: R450 A6X2 2021 | E14: 860369052464086 | F14: ESEYE | G14: RLR | H14: 45809 | I14: ATIVO | N14: conferencia 24/04
A15: RLR RMY7H08 8713 | B15: SCANIA | C15: R450 A6X2 2021 | E15: 860369051078713 | F15: ARQIA | G15: RLR | H15: 45809 | I15: ATIVO | N15: conferencia 24/04
A16: RLR RMY7H15 8779 | B16: SCANIA | C16: R450 A6X2 2021 | E16: 860369052158779 | F16: ARQIA | G16: RLR | H16: 45809 | I16: ATIVO | N16: conferencia 24/04
A17: RLR RMY7H16 5172 | B17: SCANIA | C17: R450 A6X2 2021 | E17: 860369052145172 | F17: ARQIA | G17: RLR | H17: 45809 | I17: ATIVO | N17: conferencia 24/04
A18: RLR RMY7H19 6814 | B18: SCANIA | C18: R450 A6X2 2021 | E18: 860369052166814 | F18: ARQIA | G18: RLR | H18: 45809 | I18: ATIVO | N18: conferencia 24/04
A19: RLR RMY7H21 9620 | B19: SCANIA | C19: R450 A6X2 2021 | E19: 860369052149620 | F19: ARQIA | G19: RLR | H19: 45809 | I19: ATIVO | N19: conferencia 24/04
A20: RLR RMY7H24 7270 | B20: SCANIA | C20: R450 A6X2 2021 | E20: 860369052117270 | F20: ARQIA | G20: RLR | H20: 45809 | I20: ATIVO | N20: conferencia 24/04
A21: RLR TDN1C55 0074 | B21: SCANIA | C21: R450 A6X2 2022 | E21: 860369052140074 | F21: ARQIA | G21: RLR | H21: 45809 | I21: ATIVO | N21: conferencia 24/04
A22: RLR RTK6G80 4826 | B22: SCANIA | C22: R450 A6X2 | D22: 2022 | E22: 860369052174826 | F22: ARQIA | G22: RLR | H22: 45809 | I22: ATIVO
A23: RLR RTX3B48 5460 | B23: VOLVO | C23: FH 460 6X2T 2022 | D23: 2022 | E23: 860369052155460 | F23: ARQIA | G23: RLR | H23: 45809 | I23: ATIVO
A24: RLR RTX3B56 7879 | B24: SCANIA | C24: R450 A6X2 2022 | E24: 860369052167879 | F24: ARQIA | G24: RLR | H24: 45809 | I24: ATIVO | N24: conferencia 24/04
A25: RLR RUC9I08 1503 | B25: SCANIA | C25: R450 A6X2 2022 | E25: 860369052471503 | F25: ESEYE | G25: RLR | H25: 45809 | I25: ATIVO | N25: conferencia 24/04
A26: RLR RUC9I17 7088 | B26: SCANIA | C26: R450 A6X2 2022 | E26: 860369052137088 | F26: ARQIA | G26: RLR | H26: 45809 | I26: ATIVO | N26: conferencia 24/04
A27: RLR RUD1B78 1392 | B27: SCANIA | C27: R450 A6X2 2022 | E27: 860369052171392 | F27: ARQIA | G27: RLR | H27: 45809 | I27: ATIVO | N27: conferencia 24/04
A28: RLR RUV8G70 5544 | B28: SCANIA | C28: R450 A6X2 2022 | E28: 860369052155544 | F28: ARQIA | G28: RLR | H28: 45809 | I28: ATIVO | N28: conferencia 24/04
A29: RLR RUZ6E78 5720 | B29: SCANIA | C29: R450 A6X2 2022 | E29: 860369052115720 | F29: ARQIA | G29: RLR | H29: 45809 | I29: ATIVO | N29: conferencia 24/04
A30: RLR RVE9F97 2006 | B30: SCANIA | C30: R450 A6X2 2023 | E30: 860369052472006 | F30: ESEYE | G30: RLR | H30: 45809 | I30: ATIVO | N30: conferencia 24/04
A31: RLR RVH7A75 8093 | B31: SCANIA | C31: R450 A6X2 2023 | E31: 860369052148093 | F31: ARQIA | G31: RLR | H31: 45809 | I31: ATIVO | N31: conferencia 24/04
A32: RLR RVH7A76 0247 | B32: SCANIA | C32: R450 A6X2 2023 | E32: 860369052160247 | F32: ARQIA | G32: RLR | H32: 45809 | I32: ATIVO | N32: conferencia 24/04
A33: RLR RVL9J51 8182 | B33: SCANIA | C33: R450 A6X2 2023 | E33: 860369052168182 | F33: ARQIA | G33: RLR | H33: 45809 | I33: ATIVO | N33: conferencia 24/04
A34: RLR RVP7G23 0249 | B34: SCANIA | C34: R450 A6X2 2023 | E34: 860369052140249 | F34: ARQIA | G34: RLR | H34: 45809 | I34: ATIVO | N34: conferencia 24/04
A35: RLR RVS2G41 6834 | B35: SCANIA | C35: R450 A6X2 2023 | E35: 860369052126834 | F35: ARQIA | G35: RLR | H35: 45809 | I35: ATIVO | N35: conferencia 24/04
... A42: RLR RVZ2C73 2022 | B42: SCANIA | C42: R450 A6X2 2023 | E42: 860369052145297 | F42: ARQIA | G42: RLR | H42: 45809 | I42: ATIVO | N42: conferencia 24/04
A43: RLR RVZ2C77 3661 | B43: VOLVO | C43: FH 460 6X2T 2023 | D43: 2023 | E43: 860369054153661 | F43: ESEYE | G43: RLR | H43: 45809 | I43: ATIVO
A44: RLR SHY8G25 0555 | B44: VOLVO | C44: FH 460 6X2T 2023 | D44: 2023 | E44: 860369052460555 | F44: ARQIA | G44: RLR | H44: 45809 | I44: ATIVO
A45: RLR SIA8J54 0378 | B45: IVECO | C45: S-WAY 480-6X2 2023 | E45: 860369052170378 | F45: ARQIA | G45: RLR | H45: 45809 | I45: ATIVO | N45: conferencia 24/04
A46: RLR SIU9F47 9430 | B46: IVECO | C46: S-WAY 480-6X2 | D46: 2023 | E46: 860369052149430 | F46: ARQIA | G46: RLR | H46: 45809 | I46: ATIVO
A47: RLR SJA2I72 5214 | B47: SCANIA | C47: R460 A6X2 2024 | E47: 860369052145214 | F47: ARQIA | G47: RLR | H47: 45809 | I47: ATIVO | N47: conferencia 24/04
A48: RLR SJG8D23 5107 | B48: SCANIA | C48: R460 A6X2 2024 | E48: 860369052145107 | F48: ARQIA | G48: RLR | H48: 45809 | I48: ATIVO | N48: conferencia 24/04
A49: RLR SJG8D25 5369 | B49: SCANIA | C49: G370 A6X2 2024 | E49: 860369052415369 | F49: ESEYE | G49: RLR | H49: 45809 | I49: ATIVO | N49: conferencia 24/04
A50: RLR RVA4G63 5592 | B50: SCANIA | C50: R460 A6X2 2024 | E50: 860369052405592 | F50: ESEYE | G50: RLR | H50: 45809 | I50: ATIVO | K50: Cavalo de teste | N50: conferencia 24/04
A51: RLR SJI8D74 7907 | B51: SCANIA | C51: R460 A6X2 2024 | E51: 860369052467907 | F51: ESEYE | G51: RLR | H51: 45809 | I51: ATIVO | N51: conferencia 24/04
A52: RLR SYF1B41 6749 | B52: SCANIA | C52: R460 A6X2 2024 | E52: 860369052166749 | F52: ARQIA | G52: RLR | H52: 45809 | I52: ATIVO
A53: RLR SYF1B47 4547 | B53: SCANIA | C53: R460 A6X2 2024 | E53: 860369052154547 | F53: ARQIA | G53: RLR | H53: 45809 | I53: ATIVO | N53: conferencia 24/04
A54: RLR SYF1B53 1122 | B54: SCANIA | C54: R460 A6X2 | D54: 2024 | E54: 860369052141122 | F54: ARQIA | G54: RLR | H54: 45809 | I54: ATIVO
A55: RLR SYK3G01 4019 | B55: SCANIA | C55: R460 A6X2 2024 | E55: 860369052144019 | F55: ARQIA | G55: RLR | H55: 45809 | I55: ATIVO | N55: conferencia 24/04
A56: RLR SYO4G93 0766 | B56: SCANIA | C56: R460 A6X2 2024 | E56: 860369052170766 | F56: ARQIA | G56: RLR | H56: 45809 | I56: ATIVO | N56: conferencia 24/04
A57: RLR SYO4G98 4969 | B57: SCANIA | C57: R460 A6X2 2024 | E57: 860369052144969 | F57: ESEYE | G57: RLR | H57: 45809 | I57: ATIVO | N57: conferencia 24/04
A58: RLR SYR7C56 6401 | B58: SCANIA | C58: R460 A6X2 2024 | E58: 860369052156401 | F58: ARQIA | G58: RLR | H58: 45809 | I58: ATIVO | N58: conferencia 24/04
A59: RLR SYR7C82 54794 | B59: SCANIA | C59: R460 A6X2 2024 | E59: 860369052154794 | F59: ARQIA | G59: RLR | H59: 45809 | I59: ATIVO | N59: conferencia 24/04
A60: RLR SYR7C92 6377 | B60: SCANIA | C60: R460 A6X2 2024 | E60: 860369052156377 | F60: ESEYE | G60: RLR | H60: 45809 | I60: ATIVO | N60: conferencia 24/04
A61: RLR TCE0A10 9647 | B61: SCANIA | C61: R460 A6X2 | D61: 2024 | E61: 860369052139647 | F61: ARQIA | G61: RLR | H61: 45809 | I61: ATIVO
A62: RLR TCU5I71 2047 | B62: VOLVO | C62: FH 500 6X2T 2025 | D62: 2025 | E62: 860369052142047 | F62: ARQIA | G62: RLR | H62: 45809 | I62: ATIVO
A63: RLR TCU5I75 5536 | B63: VOLVO | C63: FH 500 6X2T 2025 | D63: 2025 | E63: 860369052155536 | F63: ARQIA | G63: RLR | H63: 45809 | I63: ATIVO
A64: RLR TCW4I40 4768 | B64: VOLVO | C64: FH 500 6X2T 2025 | D64: 2025 | E64: 860369052174768 | F64: ARQIA | G64: RLR | H64: 45809 | I64: ATIVO
A65: RLR TDD5A74 2502 | B65: VOLVO | C65: FH 500 6X2T 2025 | D65: 2025 | E65: 860369052122502 | F65: ARQIA | G65: RLR | H65: 45809 | I65: ATIVO
A66: RLR TDD5A78 4758 | B66: VOLVO | C66: FH 500 6X2T 2025 | D66: 2025 | E66: 860369052434758 | F66: ARQIA | G66: RLR | H66: 45809 | I66: ATIVO
A67: RLR TDI5E39 6327 | B67: VOLVO | C67: FH 500 6X2T 2025 | D67: 2025 | E67: 860369052406327 | F67: ARQIA | G67: RLR | H67: 45809 | I67: ATIVO
A68: RLR TDJ2G89 3637 | B68: SCANIA | C68: R460 A6X2 2025 | E68: 860369052423637 | F68: ARQIA | G68: RLR | H68: 45809 | I68: ATIVO | N68: conferencia 24/04
A69: RLR TDN1C45 6443 | B69: SCANIA | C69: R460 A6X2 2025 | E69: 860369052156443 | F69: ARQIA | G69: RLR | H69: 45809 | I69: ATIVO | N69: conferencia 24/04
A70: RLR TDN1C49 4474 | B70: SCANIA | C70: R460 A6X2 2025 | E70: 860369052124474 | F70: ARQIA | G70: RLR | H70: 45809 | I70: ATIVO | N70: conferencia 24/04
A71: LNR TUA0D34 1305 | B71: VOLVO | C71: FH 540 6X4T | D71: 2024 | E71: 860369052471305 | F71: ESEYE | G71: GERDAU LENARGE | H71: 45839 | I71: ATIVO | N71: conferencia 24/04
A72: LNR TTF1D32 4128 | B72: VOLVO | C72: FH 540 6X4T | D72: 2024 | E72: 860369052464128 | F72: ESEYE | G72: GERDAU LENARGE | H72: 45839 | I72: ATIVO | N72: conferencia 24/04
A73: LNR TTF1D33 1897 | B73: VOLVO | C73: FH 540 6X4T | D73: 2024 | E73: 860369052171897 | F73: ESEYE | G73: GERDAU LENARGE | H73: 45839 | I73: ATIVO | N73: conferencia 24/04
A74: LNR TUU0D09 4099 | B74: VOLVO | C74: FH 540 6X4T | D74: 2024 | E74: 860369052174099 | F74: ARQIA | G74: GERDAU LENARGE | H74: 45839 | I74: ATIVO | N74: conferencia 24/04
A75: LNR TUA0D35 7956 | B75: VOLVO | C75: FH 540 6X4T | D75: 2024 | E75: 860369052467956 | F75: ESEYE | G75: GERDAU LENARGE | H75: 45839 | I75: ATIVO | N75: conferencia 24/04
A76: LNR TTE2C03 4810 | B76: VOLVO | C76: FH 540 6X4T | D76: 2024 | E76: 860369052154810 | F76: ARQIA | G76: GERDAU LENARGE | H76: 45839 | I76: ATIVO | N76: conferencia 24/04
A77: LNR TTQ0D36 7239 | B77: VOLVO | C77: FH 540 6X4T | D77: 2024 | E77: 860369052457239 | F77: ESEYE | G77: GERDAU LENARGE | H77: 45839 | I77: ATIVO | N77: conferencia 24/04
A78: LNR TTC3A52 2385 | B78: VOLVO | C78: FH 540 6X4T | D78: 2024 | E78: 860369052142385 | F78: ARQIA | G78: GERDAU LENARGE | H78: 45839 | I78: ATIVO | N78: conferencia 24/04
A79: LNR TTE2C07 9780 | B79: VOLVO | C79: FH 540 6X4T | D79: 2024 | E79: 860369052109780 | F79: ARQIA | G79: GERDAU LENARGE | H79: 45839 | I79: ATIVO | N79: conferencia 24/04
A80: LNR TTF1D34 7267 | B80: VOLVO | C80: FH 540 6X4T | D80: 2024 | E80: 860369052167267 | F80: ARQIA | G80: GERDAU LENARGE | H80: 45839 | I80: ATIVO | N80: conferencia 24/04
A81: LNR TUJ0D00 4520 | B81: VOLVO | C81: FH 540 6X4T | D81: 2024 | E81: 860369052404520 | F81: ARQIA | G81: GERDAU LENARGE | H81: 45839 | I81: ATIVO | N81: conferencia 24/04
A82: LNR TTG0D30 3281 | B82: VOLVO | C82: FH 540 6X4T | D82: 2024 | E82: 860369052173281 | F82: ESEYE | G82: GERDAU LENARGE | H82: 45839 | I82: ATIVO | N82: conferencia 24/04
... A88: LNR TTE2C08 9298 | B88: VOLVO | C88: FH 540 6X4T | D88: 2024 | E88: 860369052159298 | F88: ARQIA | G88: GERDAU LENARGE | H88: 45839 | I88: ATIVO | N88: conferencia 24/04
A89: LNR TUK0D47 4068 | B89: VOLVO | C89: FH 540 6X4T | D89: 2024 | E89: 860369052144068 | F89: ARQIA | G89: GERDAU LENARGE | H89: 45839 | I89: ATIVO | L89: Falha de freio- reenviado config 30-10 | N89: conferencia 24/04
A90: LNR TTC3A50 8760 | B90: VOLVO | C90: FH 540 6X4T | D90: 2024 | E90: 860369052168760 | F90: ARQIA | G90: GERDAU LENARGE | H90: 45839 | I90: ATIVO | N90: conferencia 24/04
A91: LNR TTQ0D35 8328 | B91: VOLVO | C91: FH 540 6X4T | D91: 2024 | E91: 860369052458328 | F91: ESEYE | G91: GERDAU LENARGE | H91: 45839 | I91: ATIVO | N91: conferencia 24/04
A92: LNR TTG0D28 2119 | B92: VOLVO | C92: FH 540 6X4T | D92: 2024 | E92: 860369052172119 | F92: ARQIA | G92: GERDAU LENARGE | H92: 45839 | I92: ATIVO | N92: conferencia 24/04
A93: LNR TTE2C05 4690 | B93: VOLVO | C93: FH 540 6X4T | D93: 2024 | E93: 860369052104690 | F93: ARQIA | G93: GERDAU LENARGE | H93: 45839 | I93: ATIVO | N93: conferencia 24/04
A94: LNR TTD2I71 7258 | B94: VOLVO | C94: FH 540 6X4T | D94: 2024 | E94: 860369052177258 | F94: ARQIA | G94: GERDAU LENARGE | H94: 45839 | I94: ATIVO | N94: conferencia 24/04
A95: LNR TTG0D27 7816 | B95: VOLVO | C95: FH 540 6X4T | D95: 2024 | E95: 860369052467816 | F95: ESEYE | G95: GERDAU LENARGE | H95: 45839 | I95: ATIVO | N95: conferencia 24/04
A96: LNR TUU0D10 2296 | B96: VOLVO | C96: FH 540 6X4T | D96: 2024 | E96: 860369052122296 | F96: ARQIA | G96: GERDAU LENARGE | H96: 45839 | I96: ATIVO | N96: conferencia 24/04
A97: LNR TTD2I72 7515 | B97: VOLVO | C97: FH 540 6X4T | D97: 2024 | E97: 860369052167515 | F97: ARQIA | G97: GERDAU LENARGE | H97: 45839 | I97: ATIVO | N97: conferencia 24/04
A98: LNR SSE4I48 4737 | B98: VOLVO | C98: FH 540 6X4T | D98: 2024 | E98: 860369052154737 | F98: ARQIA | G98: GERDAU LENARGE | H98: 45839 | I98: ATIVO | N98: conferencia 24/04
A99: LNR TTQ0D37 6821 | B99: VOLVO | C99: FH 540 6X4T | D99: 2024 | E99: 860369052176821 | F99: ARQIA | G99: GERDAU LENARGE | H99: 45839 | I99: ATIVO | N99: conferencia 24/04
A100: LNR TTF1D35 3815 | B100: VOLVO | C100: FH 540 6X4T | D100: 2024 | E100: 860369052203815 | F100: ESEYE | G100: GERDAU LENARGE | H100: 45839 | I100: ATIVO | N100: conferencia 24/04
A101: LNR TUK0D46 0009 | B101: VOLVO | C101: FH 540 6X4T | D101: 2024 | E101: 860369052140009 | F101: ESEYE | G101: GERDAU LENARGE | H101: 45839 | I101: ATIVO | N101: conferencia 24/04
... A103: LNR TTC3A51 7524 | B103: VOLVO | C103: FH 540 6X4T | D103: 2024 | E103: 860369052157524 | F103: ARQIA | G103: GERDAU LENARGE | H103: 45839 | I103: ATIVO | N103: conferencia 24/04
A104: APR RTK2D54 1227 | B104: MERCEDES BENZ | C104: Axor 2544 | D104: 2022 | E104: 860369054161227 | F104: ESEYE | G104: APERAM Carvão | H104: 45887 | I104: ATIVO
A105: APR RTX1H314016 | B105: MERCEDES BENZ | C105: Axor 2544 | D105: 2022 | E105: 860369054154016 | F105: ESEYE | G105: APERAM Carvão | H105: 45887 | I105: ATIVO
A106: APR RTX1H32 9411 | B106: MERCEDES BENZ | C106: Axor 2544 | D106: 2022 | E106: 860369054159411 | F106: ESEYE | G106: APERAM Carvão | H106: 45887 | I106: ATIVO
A107: APR RTX1H33 0657 | B107: MERCEDES BENZ | C107: Axor 2544 | D107: 2022 | E107: 860369054170657 | F107: ESEYE | G107: APERAM Carvão | H107: 45887 | I107: ATIVO
A108: APR RTX2C42 9072 | B108: MERCEDES BENZ | C108: Axor 2544 | D108: 2022 | E108: 860369054159072 | F108: ESEYE | G108: APERAM Carvão | H108: 45887 | I108: ATIVO
A109: APR RTX2J94 7499 | B109: MERCEDES BENZ | C109: Axor 2544 | D109: 2022 | E109: 860369052167499 | F109: ESEYE | G109: APERAM Carvão | H109: 45887 | I109: ATIVO
A110: APR RTX2J95 1457 | B110: MERCEDES BENZ | C110: Axor 2544 | D110: 2022 | E110: 860369054171457 | F110: ESEYE | G110: APERAM Carvão | H110: 45887 | I110: ATIVO
A111: APR RTX2J98 6574 | B111: MERCEDES BENZ | C111: Axor 2544 | D111: 2022 | E111: 860369052166574 | F111: ESEYE | G111: APERAM Carvão | H111: 45887 | I111: ATIVO
A112: APR RTX2J99 4559 | B112: MERCEDES BENZ | C112: Axor 2544 | D112: 2022 | E112: 860369054184559 | F112: ESEYE | G112: APERAM Carvão | H112: 45887 | I112: ATIVO
...

Sheet Interações
A1: Data | B1: Cliente | C1: Responsável | D1: Tipo | E1: Observação | F1: Próximo passo | G1: Data próx. passo
A2: 45981 | B2: APERAM Carvão | C2: Diego | D2: Treinamento | E2: Todos os instrutores devidamente treinados.
A3: 46029 | B3: BEIRA RIO | C3: Diego | D3: Reunião | E3: Reunião virtual
A4: 46031 | B4: GTS | C4: Leonardo | D4: Reunião | E4: Reunião comercial presencial e apresentação dos resultados
A5: 46031 | B5: APERAM Carvão | C5: Leonardo | D5: Reunião | E5: Reunião comercial
A6: 46036 | B6: P&W | C6: Leonardo | D6: Reunião | E6: Reunião comercial presencial e apresentação dos resultados
A7: 46036 | B7: EXPRESSO TRANSPORTE | C7: Leonardo | D7: Reunião | E7: Reunião comercial
A8: 46037 | B8: TRANSFAL | C8: Leonardo | D8: Reunião | E8: Reunião comercial para prospecção
A9: 46038 | B9: P&W | C9: Diego | D9: Treinamento | E9: Condução assistida - Veículo QNK3665
A10: 46045 | B10: DNA | C10: Diego | D10: Treinamento | E10: Condução assistida - Veículo TCK1C56
A11: 46051 | B11: DNA | C11: Diego | D11: Treinamento | E11: Condução assistida - Veículo RUK6F59
A12: 46056 | B12: BRITO SERVIÇO | C12: Diego | D12: Visita | E12: Condução assistida e aplicação dos parâmetros
A13: 46057 | B13: P&W | C13: Diego | D13: Treinamento | E13: Condução assistida e aplicação dos parâmetros
... A83: 46206 | B83: APERAM Madeira | C83: FACSS | D83: Reunião | E83: Apresentação comercial do sistema e dos resultados
A84: 46210 | B84: PLENA | C84: FACSS | D84: Reunião | E84: Apresentação comercial dos resultados da POC | F84: Proposta comercial (Guilherme)
A85: 46211 | B85: HERTEX | C85: Diego | D85: Treinamento | E85: Condução assistida e aplicação dos parâmetros
A86: 46213 | B86: P&W | C86: FACSS | D86: Reunião | E86: Reunião virtual para entender dúvidas sobre o contrato
A87: 46216 | B87: APERAM Carvão | C87: Pablo | D87: Reunião | E87: Reunião virtual para entender dúvidas sobre o sistema
A88: 46216 | B88: EMF LOGÍSTICA | C88: FACSS | D88: Suporte | E88: Retirada dos módulos e suspensão da POC
A89: 46216 | B89: TRANSPORTADORA NOVA ERA | C89: FACSS | D89: Suporte | E89: Retirada dos módulos e suspensão da POC
A90: 46216 | B90: TRANSKOMPA | C90: FACSS | D90: Suporte | E90: Retirada dos módulos e suspensão da POC
A91: 46216 | B91: CONFINS | C91: FACSS | D91: Suporte | E91: Conversa em andamento para início da POC
A92: 46216 | B92: VALLENCE | C92: Carlos Eduardo | D92: Interação | E92: Cliente mostrou intesse na Jornada de Trabalho
A93: 46216 | B93: ÁGUA BONITA | C93: Diego | D93: Interação | E93: Sem observações.
A94: 46216 | B94: APERAM Carvão | C94: Guilherme | D94: Interação | E94: Próximos da virada para Telemetria II.
A95: 46216 | B95: APERAM Madeira | C95: Pablo | D95: Interação | E95: Validando apresentação comercial.
A96: 46216 | B96: BEIRA RIO | C96: Rebeca | D96: Interação | E96: Iniciar faturamento.
A97: 46216 | B97: CONFINS | C97: Guilherme | D97: Interação | E97: Puxaremos a POC nessa semana. | F97: Agendar POC
A98: 46216 | B98: EMF LOGÍSTICA | C98: Guilherme | D98: Interação | E98: Retirada de módulos.
A99: 46216 | B99: EXPRESSO TRANSPORTE | C99: Diego | D99: Interação | E99: Sem observações.
A100: 46217 | B100: FASI | C100: Diego | D100: Treinamento | E100: Condução assistida e aplicação dos parâmetros
A101: 46218 | B101: P&W | C101: FACSS | D101: Reunião | E101: Reunião presencial para esclarecer dúvidas sobre o contrato
A102: 46218 | B102: JAF | C102: Diego | D102: Treinamento | E102: Treinando sobre o uso da plataforma versão mobile
A103: 46219 | B103: APERAM Carvão | C103: Pablo | D103: Suporte | E103: Tira dúvidas e treinamento sobre plataforma I
A104: 46219 | B104: VALLENCE | C104: Carlos Eduardo | D104: Interação | E104: Apresentação da Jornada de Trabalho
A105: 46220 | B105: SEMPRE VOLTA | C105: Gabriel | D105: Suporte | E105: Reunião online e suporte sobre o uso da vinculação retroativa
A106: 46226 | B106: EXPRESSO TRANSPORTE | C106: Diego | D106: Interação | E106: Entender o porquê não estamos faturando | F106: Envolver Diego e Rebeca na conversa.
A107: 46230 | B107: EXPRESSO TRANSPORTE | C107: Diego | D107: Interação | E107: Conversa iniciada para começarmos o treinamento
A108: 46231 | B108: HERTEX | C108: Diego | D108: Visita | E108: Visita comercial ao cliente para tentar evoluir comercialmente
A109: 46232 | B109: JAF | C109: Diego | D109: Treinamento | E109: Visita semanal de treinamento
A110: 46233 | B110: APERAM Madeira | C110: Pablo | D110: Interação | E110: Interação comercial | F110: Fazer contato para reunião
A111: 46233 | B111: APERAM Carvão | C111: Pablo | D111: Interação | E111: Transição para o T2
A112: 46233 | B112: NOVA MINERAIS | C112: Diego | D112: Interação | E112: Empresa sem contrato e sem dados estratégicos | F112: Entender a relação ARJON <> FACSS com o Guilherme
A113: 46233 | B113: PORTINARI | C113: Reinaldo | D113: Suporte | E113: Desinstalações | F113: Concluir desinstalações
A114: 46233 | B114: EMF LOGÍSTICA | C114: Reinaldo | D114: Suporte | E114: Dificuldade por parte da empresa no processo das desinstalações | F114: Concluir desinstalações
A115: 46233 | B115: TRANSPORTADORA NOVA ERA | C115: Reinaldo | D115: Suporte | E115: A própria empresa está retirando os módulos, devido dificuldades logísticas | F115: Concluir desinstalações
A116: 46233 | B116: TRANSKOMPA | C116: Reinaldo | D116: Suporte | E116: A própria empresa está retirando os módulos, devido dificuldades logísticas | F116: Concluir desinstalações
A117: 46233 | B117: WD AGROINDUSTRIAL | C117: Reinaldo | D117: Suporte | E117: Iniciar processo das desinstalações | F117: Concluir desinstalações
A118: 46233 | B118: EXPRESSO TRANSPORTE | C118: Diego | D118: Interação | E118: Instalações concluídas | F118: Iniciar processo de treinamento
A119: 46233 | B119: EXPRESSO TRANSPORTE | C119: Diego | D119: Interação | E119: Veículo HND8D73 com problema na bomba de combustível e isso pode ser assunto para travar processos | F119: Cliente deve dar a manutenção devida
A120: 46233 | B120: VALLENCE | C120: Diego | D120: Treinamento | E120: Dificuldade em utilizar a plataforma | F120: Sugerir uma nova capacitação para utilizar o sistema
A121: 46240 | B121: JAF | C121: Diego | D121: Treinamento | E121: Visita semanal de treinamento
A122: 46240 | B122: VALLENCE | C122: FACSS | D122: Suporte | E122: Premiação dos motoristas | F122: Correção dos indicadores
A123: 46241 | B123: CONFINS | C123: Diego | D123: Reunião | E123: Apresentação comercial da POC | F123: Contato do setor de proposta comercial
A124: 46241 | B124: CONFINS | C124: Diego | D124: Interação | E124: Entrega de PDF com resumo da apresentação comercial presencial que ocorreu no dia 06/08 | F124: Contato do setor de proposta comercial
A125: 46247 | B125: NOVA MINERAIS | C125: Rebeca | D125: Suporte | E125: Correr atrás de assinatura do contrato | F125: Procurar o Guilherme
A126: 46247 | B126: EMF LOGÍSTICA | C126: Reinaldo | D126: Suporte | E126: Dificuldade por parte da empresa no processo das desinstalações | F126: Concluir desinstalações
A127: 46247 | B127: TRANSKOMPA | C127: Reinaldo | D127: Suporte | E127: A própria empresa está retirando os módulos, devido dificuldades logísticas | F127: Concluir desinstalações
A128: 46247 | B128: WD AGROINDUSTRIAL | C128: Reinaldo | D128: Suporte | E128: Iniciar processo das desinstalações | F128: Concluir desinstalações

Sheet T&D
B2: TREINAMENTO, DESENVOLVIMENTO & ACOMPANHAMENTO
B3: =COUNTIF(B11:B225,"PROCESSANDO")+COUNTIF(B11:B225,"A FAZER") -> 3
C4: =COUNTIFS(D24:D225,"TREINAMENTO / VISITA",L24:L225,"CONCLUÍDO") -> 84 | D4: =COUNTIF(Clientes!B2:B51,"ATIVO") -> 16 | E4: CLIENTES | F4: =COUNTIF(Clientes!B2:B51,"PERÍODO DE TESTE") -> 5 | G4: =COUNTIF(Clientes!B2:B51,"PROSPECÇÃO") -> 6 | H4: =COUNTIFS('Módulos'!$B$2:$B$2464,I4,'Módulos'!$I$2:$I$2464,"ATIVO") -> 3 | I4: CATERPILLAR | J4: =COUNTIFS('Módulos'!$B$2:$B$2464,K4,'Módulos'!$I$2:$I$2464,"ATIVO") -> 1 | K4: KOMATSU | L4: =COUNTIFS('Módulos'!$B$2:$B$2464,M4,'Módulos'!$I$2:$I$2464,"ATIVO") -> 0 | M4: SANY
C5: TREINAMENTOS REALIZADOS | F5: FROTAS EM TESTE | G5: FROTAS EM PROSPECÇÃO | H5: =COUNTIFS('Módulos'!$B$2:$B$2464,I5,'Módulos'!$I$2:$I$2464,"ATIVO") -> 224 | I5: DAF | J5: =COUNTIFS('Módulos'!$B$2:$B$2464,K5,'Módulos'!$I$2:$I$2464,"ATIVO") -> 0 | K5: MAN | L5: =COUNTIFS('Módulos'!$B$2:$B$2464,M5,'Módulos'!$I$2:$I$2464,"ATIVO") -> 197 | M5: SCANIA
B6: DEMANDAS EM ABERTO | C6: =COUNTIF(B24:B227,"FINALIZADO") -> 198 | D6: =SUM(H4:H7)+SUM(J4:J7)+SUM(L4:L7) -> 2092 | E6: MÓDULOS | F6: =COUNTIF(Clientes!B2:B51,"POC SEM EVOLUÇÃO") -> 10 | G6: =COUNTIF(Clientes!B2:B51,"INATIVO") -> 3 | H6: =COUNTIFS('Módulos'!$B$2:$B$2464,I6,'Módulos'!$I$2:$I$2464,"ATIVO") -> 12 | I6: IVECO | J6: =COUNTIFS('Módulos'!$B$2:$B$2464,K6,'Módulos'!$I$2:$I$2464,"ATIVO") -> 99 | K6: MERCEDES BENZ | L6: =COUNTIFS('Módulos'!$B$2:$B$2464,M6,'Módulos'!$I$2:$I$2464,"ATIVO") -> 63 | M6: VOLKSWAGEN
C7: DEMANDAS ATENDIDAS | F7: POCs SEM SUCESSO | G7: FROTAS INATIVAS | H7: =COUNTIFS('Módulos'!$B$2:$B$2464,I7,'Módulos'!$I$2:$I$2464,"ATIVO") -> 1 | I7: JAC | J7: =COUNTIFS('Módulos'!$B$2:$B$2464,K7,'Módulos'!$I$2:$I$2464,"ATIVO") -> 1 | K7: NANJING | L7: =COUNTIFS('Módulos'!$B$2:$B$2464,M7,'Módulos'!$I$2:$I$2464,"ATIVO") -> 1491 | M7: VOLVO
B9: STATUS | C9: EMPRESA | D9: DEMANDA | K9: ANDAMENTO
B11: MONITORAMENTO | C11: COOPERAUTO | D11: PROSPECÇÃO | K11: 46265 | L11: =IF(K11="","APONTAR DATA",(IF('T&D'!B11="FINALIZADO", "CONCLUÍDO", IF(K11<TODAY(), "VENCIDO", IF(K11=TODAY(), "VENCE HOJE", IF(K11<=TODAY()+5,"VENCENDO", "NO PRAZO")))))) -> NO PRAZO
C12: DELLMAR
C13: MALIBU
C14: TRANSNIEL
C15: TRANSPORTADORA IRMÃOS GOMES
C16: TRANSODILON
C17: APERAM Madeira | D17: POC
C18: CONFINS
C19: FASI
C20: HERTEX
C21: PLENA
C22: TRANSMOREIRA | D22: ESTUDO DE CASO
C23: ZERO CARBON
B24: FINALIZADO | C24: EMF LOGÍSTICA | D24: TREINAMENTO / VISITA | E24: APLICAR A CONDUÇÃO FACSS, SANAR DÚVIDAS SURGIDAS E FAZER ESTUDO DE CASO | K24: 45945 | L24: =IF(K24="","APONTAR DATA",(IF('T&D'!B24="FINALIZADO", "CONCLUÍDO", IF(K24<TODAY(), "VENCIDO", IF(K24=TODAY(), "VENCE HOJE", IF(K24<=TODAY()+5,"VENCENDO", "NO PRAZO")))))) -> CONCLUÍDO
B25: FINALIZADO | C25: APERAM Carvão | D25: TREINAMENTO / VISITA | E25: DIREÇÃO ASSISTIDA | K25: 45946 | L25: =IF(K25="","APONTAR DATA",(IF('T&D'!B25="FINALIZADO", "CONCLUÍDO", IF(K25<TODAY(), "VENCIDO", IF(K25=TODAY(), "VENCE HOJE", IF(K25<=TODAY()+5,"VENCENDO", "NO PRAZO")))))) -> CONCLUÍDO
B26: FINALIZADO | C26: APERAM Carvão | D26: TREINAMENTO / VISITA | E26: DIREÇÃO ASSISTIDA | K26: 45947 | L26: =IF(K26="","APONTAR DATA",(IF('T&D'!B26="FINALIZADO", "CONCLUÍDO", IF(K26<TODAY(), "VENCIDO", IF(K26=TODAY(), "VENCE HOJE", IF(K26<=TODAY()+5,"VENCENDO", "NO PRAZO")))))) -> CONCLUÍDO
B27: FINALIZADO | C27: RLR | D27: TREINAMENTO / VISITA | E27: APRESENTAR A OPERAÇÃO AO PM E FAZER ESTUDO DE CASO | K27: 45958 | L27: =IF(K27="","APONTAR DATA",(IF('T&D'!B27="FINALIZADO", "CONCLUÍDO", IF(K27<TODAY(), "VENCIDO", IF(K27=TODAY(), "VENCE HOJE", IF(K27<=TODAY()+5,"VENCENDO", "NO PRAZO")))))) -> CONCLUÍDO
B28: FINALIZADO | C28: APERAM Carvão | D28: TREINAMENTO / VISITA | E28: DIREÇÃO ASSISTIDA | K28: 45960 | L28: =IF(K28="","APONTAR DATA",(IF('T&D'!B28="FINALIZADO", "CONCLUÍDO", IF(K28<TODAY(), "VENCIDO", IF(K28=TODAY(), "VENCE HOJE", IF(K28<=TODAY()+5,"VENCENDO", "NO PRAZO")))))) -> CONCLUÍDO
B29: FINALIZADO | C29: APERAM Carvão | D29: TREINAMENTO / VISITA | E29: DIREÇÃO ASSISTIDA | K29: 45961 | L29: =IF(K29="","APONTAR DATA",(IF('T&D'!B29="FINALIZADO", "CONCLUÍDO", IF(K29<TODAY(), "VENCIDO", IF(K29=TODAY(), "VENCE HOJE", IF(K29<=TODAY()+5,"VENCENDO", "NO PRAZO")))))) -> CONCLUÍDO
B30: FINALIZADO | C30: TRANSKOMPA | D30: TREINAMENTO / VISITA | E30: DIREÇÃO ASSISTIDA | K30: 45966 | L30: =IF(K30="","APONTAR DATA",(IF('T&D'!B30="FINALIZADO", "CONCLUÍDO", IF(K30<TODAY(), "VENCIDO", IF(K30=TODAY(), "VENCE HOJE", IF(K30<=TODAY()+5,"VENCENDO", "NO PRAZO")))))) -> CONCLUÍDO
B31: FINALIZADO | C31: PORTINARI | D31: TREINAMENTO / VISITA | E31: APRESENTAÇÃO DA TELEMETRIA E CONDUÇÃO FACSS | K31: 45975 | L31: =IF(K31="","APONTAR DATA",(IF('T&D'!B31="FINALIZADO", "CONCLUÍDO", IF(K31<TODAY(), "VENCIDO", IF(K31=TODAY(), "VENCE HOJE", IF(K31<=TODAY()+5,"VENCENDO", "NO PRAZO")))))) -> CONCLUÍDO
B32: FINALIZADO | C32: APERAM Carvão | D32: TREINAMENTO / VISITA | E32: DIREÇÃO ASSISTIDA | K32: 45978 | L32: =IF(K32="","APONTAR DATA",(IF('T&D'!B32="FINALIZADO", "CONCLUÍDO", IF(K32<TODAY(), "VENCIDO", IF(K32=TODAY(), "VENCE HOJE", IF(K32<=TODAY()+5,"VENCENDO", "NO PRAZO")))))) -> CONCLUÍDO
B33: FINALIZADO | C33: APERAM Carvão | D33: TREINAMENTO / VISITA | E33: DIREÇÃO ASSISTIDA | K33: 45979 | L33: =IF(K33="","APONTAR DATA",(IF('T&D'!B33="FINALIZADO", "CONCLUÍDO", IF(K33<TODAY(), "VENCIDO", IF(K33=TODAY(), "VENCE HOJE", IF(K33<=TODAY()+5,"VENCENDO", "NO PRAZO")))))) -> CONCLUÍDO
B34: FINALIZADO | C34: APERAM Carvão | D34: TREINAMENTO / VISITA | E34: DIREÇÃO ASSISTIDA | K34: 45980 | L34: =IF(K34="","APONTAR DATA",(IF('T&D'!B34="FINALIZADO", "CONCLUÍDO", IF(K34<TODAY(), "VENCIDO", IF(K34=TODAY(), "VENCE HOJE", IF(K34<=TODAY()+5,"VENCENDO", "NO PRAZO")))))) -> CONCLUÍDO
B35: FINALIZADO | C35: EMF LOGÍSTICA | D35: TREINAMENTO / VISITA | E35: APRESENTAÇÃO COMERCIAL E CONDUÇÃO FACSS | K35: 46014 | L35: =IF(K35="","APONTAR DATA",(IF('T&D'!B35="FINALIZADO", "CONCLUÍDO", IF(K35<TODAY(), "VENCIDO", IF(K35=TODAY(), "VENCE HOJE", IF(K35<=TODAY()+5,"VENCENDO", "NO PRAZO")))))) -> CONCLUÍDO
... B224: FINALIZADO | C224: CONFINS | D224: DEMANDA INTERNA | E224: ENTREGAR APRESENTAÇÃO DA REUNIÃO | K224: 46241 | L224: =IF(K224="","APONTAR DATA",(IF('T&D'!B224="FINALIZADO", "CONCLUÍDO", IF(K224<TODAY(), "VENCIDO", IF(K224=TODAY(), "VENCE HOJE", IF(K224<=TODAY()+5,"VENCENDO", "NO PRAZO")))))) -> CONCLUÍDO
L225: =IF(K225="","APONTAR DATA",(IF('T&D'!B225="FINALIZADO", "CONCLUÍDO", IF(K225<TODAY(), "VENCIDO", IF(K225=TODAY(), "VENCE HOJE", IF(K225<=TODAY()+5,"VENCENDO", "NO PRAZO")))))) -> APONTAR DATA

Sheet Config
A1: Listas e parâmetros (não apagar) — edite o Ticket em P2
A2: Status | B2: Faturamento | C2: Nível de acesso | D2: Fidelidade | E2: Módulos | F2: Treinamento | G2: Evolução | H2: Sistema de Jornada | I2: Responsável | J2: Estágio funil | K2: Probabilidade | L2: Canal | M2: Prioridade | N2: Tipo interação | O2: Ticket (R$/veículo/mês) | P2: 150
A3: Ativo | B3: Faturando | C3: Telemetria I | D3: Fidelidade 12 meses | E3: Módulos operando | F3: Capacitação Efetiva | G3: Com evolução | H3: AIKO | I3: Carlos Eduardo | J3: Lead | K3: 0.05 | L3: Outbound LinkedIn | M3: A | N3: Cobrança | O3: Premissa: edite com seu ticket real. Usado no valor ponderado do Pipeline.
A4: Inativo | B4: Sem faturar | C4: Telemetria II | D4: Sem fidelidade | E4: Checar módulos | F4: Capacitação em Desenvolvimento | G4: Sem evolução | H4: Boreal | I4: Diego | J4: Contato feito | K4: 0.1 | L4: Outbound e-mail | M4: B | N4: Interação
A5: Período de teste | B5: Faturamento inativo | C5: Sem acesso | D5: Fidelizar | E5: Telemetria suspensa | F5: Realizar Capacitação | G5: Sem dados | H5: Diário de Bordo | I5: Gabriel | J5: Diagnóstico agendado | K5: 0.25 | L5: Telefone | M5: C | N5: Reunião
A6: Proposta comercial | F6: Inativado | G6: Em POC | H6: Fastmine | I6: Guilherme | J6: Diagnóstico feito | K6: 0.4 | L6: WhatsApp | N6: Suporte
A7: Prospecção | G7: Inativado | H7: Inoprime | I7: Leonardo | J7: Proposta enviada | K7: 0.6 | L7: Indicação | N7: Treinamento
A8: Prospecção sem Sucesso | H8: Link | I8: Pablo | J8: Negociação | K8: 0.8 | L8: Evento | N8: Visita
A9: POC Sem Evolução | H9: Maxtrack | I9: Rebeca | J9: Fechado - Ganho | K9: 1 | L9: Parceria
H10: Não faz | I10: Reinaldo | J10: Fechado - Perdido | K10: 0
H11: Planilha | I11: FACSS
H12: Sascar
H13: SAT
H14: Sem dados
H15: Sistema próprio
H16: Trucks Control
